Workbook

Sheet Welcome - Instructions
A1: Interior Design Project Management Workbook
A3: Quick Start Guide
A4: Step 1: Add client/project details in Client & Project Profile. Step 2: Add rooms in Room List. Step 3: Add FF&E items in Master FF&E Schedule. Step 4: Track budget, orders, approvals, delivery, and installation. Step 5: Use Project Dashboard for overview.
A7: What Each Tab Is Used For
A8: Profile stores project details. Room List tracks rooms and budgets. Master FF&E is the core item schedule. Other tabs track furniture, fixtures, finishes, sourcing, vendors, budget, orders, delivery, approvals, timeline, tasks, measurements, contractors, invoices, and notes.
A11: How To Enter Data
A12: Type into white cells beginning on row 2. Header rows and formula columns should not be overwritten unless you intentionally customize the workbook.
A15: Color Coding
A16: Green = complete / approved / on budget. Yellow = pending / in progress. Red = overdue / over budget / delayed. Gray = cancelled / on hold.
A19: Dropdown Instructions
A20: Click cells in status/category/room/vendor/priority columns and select from dropdown menus. Room and vendor dropdowns reference the Room List and Vendor Database.
A23: Compatibility Note
... A32: Add your support email, shop URL, license terms, or client handoff notes here before selling or sharing.

Sheet Project Dashboard
A1: Project Dashboard
A3: Total project budget | D3: Total estimated cost | G3: Total actual cost | J3: Remaining budget
A4: ='Client & Project Profile'!B12 | D4: =SUM('Budget Tracker'!C2:C251) | G4: =SUM('Budget Tracker'!D2:D251) | J4: ='Client & Project Profile'!B12-SUM('Budget Tracker'!D2:D251)
A6: Budget used % | D6: Number of rooms | G6: Total FF&E items | J6: Items approved
A7: =IFERROR(SUM('Budget Tracker'!D2:D251)/'Client & Project Profile'!B12,0) | D7: =COUNTA('Room List'!A2:A251) | G7: =COUNTA('Master FF&E Schedule'!D2:D251) | J7: =COUNTIF('Master FF&E Schedule'!W2:W251,"Approved")
A9: Items ordered | D9: Items delivered | G9: Items installed | J9: Overdue tasks
A10: =COUNTIF('Master FF&E Schedule'!V2:V251,"Ordered")+COUNTIF('Master FF&E Schedule'!V2:V251,"Confirmed")+COUNTIF('Master FF&E Schedule'!V2:V251,"In production")+COUNTIF('Master FF&E Schedule'!V2:V251,"Shipped")+COUNTIF('Master FF&E Schedule'!V2:V251,"Delivered") | D10: =COUNTIF('Master FF&E Schedule'!X2:X251,"Delivered") | G10: =COUNTIF('Master FF&E Schedule'!Y2:Y251,"Installed") | J10: =COUNTIF('Task & To-Do List'!I2:I251,">0")+COUNTIF('Project Timeline'!L2:L251,">0")
A12: Pending client approvals | D12: Open vendor orders | G12: Items not ordered | J12: Delivered not installed
A13: =COUNTIF('Client Approval Tracker'!F2:F251,"Sent")+COUNTIF('Client Approval Tracker'!F2:F251,"Not sent")+COUNTIF('Master FF&E Schedule'!W2:W251,"Client review") | D13: =COUNTIF('Purchase Order Tracker'!J2:J251,"Ordered")+COUNTIF('Purchase Order Tracker'!J2:J251,"Confirmed")+COUNTIF('Purchase Order Tracker'!J2:J251,"In production")+COUNTIF('Purchase Order Tracker'!J2:J251,"Shipped")+COUNTIF('Purchase Order Tracker'!J2:J251,"Delayed") | G13: =COUNTIF('Master FF&E Schedule'!V2:V251,"Not ordered")+COUNTIFS('Master FF&E Schedule'!D2:D251,"<>",'Master FF&E Schedule'!V2:V251,"") | J13: =COUNTIFS('Master FF&E Schedule'!X2:X251,"Delivered",'Master FF&E Schedule'!Y2:Y251,"<>Installed")
A16: Budget by Room | E16: Budget vs Actual | H16: Item Status Breakdown
A17: Room | B17: Estimated | C17: Actual | E17: Metric | F17: Amount | H17: Status | I17: Count
A18: ='Room List'!A2 | B18: ='Room List'!G2 | C18: ='Room List'!H2 | E18: Budget | F18: ='Client & Project Profile'!B12 | H18: Sourcing | I18: =COUNTIF('Master FF&E Schedule'!V2:Y251,"Sourcing")
A19: ='Room List'!A3 | B19: ='Room List'!G3 | C19: ='Room List'!H3 | E19: Actual | F19: =SUM('Budget Tracker'!D2:D251) | H19: Option selected | I19: =COUNTIF('Master FF&E Schedule'!V2:Y251,"Option selected")
A20: ='Room List'!A4 | B20: ='Room List'!G4 | C20: ='Room List'!H4 | H20: Client review | I20: =COUNTIF('Master FF&E Schedule'!V2:Y251,"Client review")
A21: ='Room List'!A5 | B21: ='Room List'!G5 | C21: ='Room List'!H5 | H21: Approved | I21: =COUNTIF('Master FF&E Schedule'!V2:Y251,"Approved")
A22: ='Room List'!A6 | B22: ='Room List'!G6 | C22: ='Room List'!H6 | H22: Ordered | I22: =COUNTIF('Master FF&E Schedule'!V2:Y251,"Ordered")
A23: ='Room List'!A7 | B23: ='Room List'!G7 | C23: ='Room List'!H7 | H23: Shipped | I23: =COUNTIF('Master FF&E Schedule'!V2:Y251,"Shipped")
A24: ='Room List'!A8 | B24: ='Room List'!G8 | C24: ='Room List'!H8 | H24: Delivered | I24: =COUNTIF('Master FF&E Schedule'!V2:Y251,"Delivered")
A25: ='Room List'!A9 | B25: ='Room List'!G9 | C25: ='Room List'!H9 | H25: Installed | I25: =COUNTIF('Master FF&E Schedule'!V2:Y251,"Installed")
A26: ='Room List'!A10 | B26: ='Room List'!G10 | C26: ='Room List'!H10 | H26: Cancelled | I26: =COUNTIF('Master FF&E Schedule'!V2:Y251,"Cancelled")
A27: ='Room List'!A11 | B27: ='Room List'!G11 | C27: ='Room List'!H11 | H27: Backordered | I27: =COUNTIF('Master FF&E Schedule'!V2:Y251,"Backordered")
A28: ='Room List'!A12 | B28: ='Room List'!G12 | C28: ='Room List'!H12
A29: ='Room List'!A13 | B29: ='Room List'!G13 | C29: ='Room List'!H13
A30: ='Room List'!A14 | B30: ='Room List'!G14 | C30: ='Room List'!H14
A35: Delivery Status Breakdown | E35: Category Spend Breakdown
A36: Status | B36: Count | E36: Category | F36: Final Cost
A37: Not ordered | B37: =COUNTIF('Delivery & Installation'!G2:G251,"Not ordered") | E37: Sofa | F37: =SUMIF('Master FF&E Schedule'!C2:C251,"Sofa",'Master FF&E Schedule'!T2:T251)
A38: Ordered | B38: =COUNTIF('Delivery & Installation'!G2:G251,"Ordered") | E38: Chair | F38: =SUMIF('Master FF&E Schedule'!C2:C251,"Chair",'Master FF&E Schedule'!T2:T251)
A39: Shipped | B39: =COUNTIF('Delivery & Installation'!G2:G251,"Shipped") | E39: Table | F39: =SUMIF('Master FF&E Schedule'!C2:C251,"Table",'Master FF&E Schedule'!T2:T251)
A40: Delivered | B40: =COUNTIF('Delivery & Installation'!G2:G251,"Delivered") | E40: Bed | F40: =SUMIF('Master FF&E Schedule'!C2:C251,"Bed",'Master FF&E Schedule'!T2:T251)
A41: Delayed | B41: =COUNTIF('Delivery & Installation'!G2:G251,"Delayed") | E41: Rug | F41: =SUMIF('Master FF&E Schedule'!C2:C251,"Rug",'Master FF&E Schedule'!T2:T251)
A42: Cancelled | B42: =COUNTIF('Delivery & Installation'!G2:G251,"Cancelled") | E42: Lighting | F42: =SUMIF('Master FF&E Schedule'!C2:C251,"Lighting",'Master FF&E Schedule'!T2:T251)
A43: Returned | B43: =COUNTIF('Delivery & Installation'!G2:G251,"Returned") | E43: Artwork | F43: =SUMIF('Master FF&E Schedule'!C2:C251,"Artwork",'Master FF&E Schedule'!T2:T251)
A44: Backordered | B44: =COUNTIF('Delivery & Installation'!G2:G251,"Backordered") | E44: Mirror | F44: =SUMIF('Master FF&E Schedule'!C2:C251,"Mirror",'Master FF&E Schedule'!T2:T251)
E45: Window treatment | F45: =SUMIF('Master FF&E Schedule'!C2:C251,"Window treatment",'Master FF&E Schedule'!T2:T251)
E46: Hardware | F46: =SUMIF('Master FF&E Schedule'!C2:C251,"Hardware",'Master FF&E Schedule'!T2:T251)
E47: Plumbing fixture | F47: =SUMIF('Master FF&E Schedule'!C2:C251,"Plumbing fixture",'Master FF&E Schedule'!T2:T251)
E48: Appliance | F48: =SUMIF('Master FF&E Schedule'!C2:C251,"Appliance",'Master FF&E Schedule'!T2:T251)
E49: Decor | F49: =SUMIF('Master FF&E Schedule'!C2:C251,"Decor",'Master FF&E Schedule'!T2:T251)
E50: Textile | F50: =SUMIF('Master FF&E Schedule'!C2:C251,"Textile",'Master FF&E Schedule'!T2:T251)
E51: Cabinetry | F51: =SUMIF('Master FF&E Schedule'!C2:C251,"Cabinetry",'Master FF&E Schedule'!T2:T251)
E52: Flooring | F52: =SUMIF('Master FF&E Schedule'!C2:C251,"Flooring",'Master FF&E Schedule'!T2:T251)
E53: Wallcovering | F53: =SUMIF('Master FF&E Schedule'!C2:C251,"Wallcovering",'Master FF&E Schedule'!T2:T251)
E54: Other | F54: =SUMIF('Master FF&E Schedule'!C2:C251,"Other",'Master FF&E Schedule'!T2:T251)

Sheet Client & Project Profile
A1: Client & Project Profile
A3: Client name
A4: Client email
A5: Phone number
A6: Project name
A7: Project address
A8: Project type | B8: Residential
A9: Design style
A10: Start date
A11: Target completion date
A12: Total budget | B12: 0
A13: Designer name
A14: Client notes
A15: Scope summary
A16: Project status | B16: In progress
A17: Contract signed | B17: No
A18: Deposit paid | B18: No
A19: Design package selected
A20: Billing method | B20: Flat fee

Sheet Room List
A1: Room name | B1: Room type | C1: Floor/level | D1: Square footage | E1: Design status | F1: Budget allocation | G1: Estimated spend | H1: Actual spend | I1: Remaining budget | J1: Priority level | K1: Notes
G2: =IFERROR(SUMIF('Master FF&E Schedule'!$B:$B,$A2,'Master FF&E Schedule'!$P:$P),0) | H2: =IFERROR(SUMIF('Master FF&E Schedule'!$B:$B,$A2,'Master FF&E Schedule'!$T:$T),0) | I2: =IF($A2="","",$F2-$H2)
G3: =IFERROR(SUMIF('Master FF&E Schedule'!$B:$B,$A3,'Master FF&E Schedule'!$P:$P),0) | H3: =IFERROR(SUMIF('Master FF&E Schedule'!$B:$B,$A3,'Master FF&E Schedule'!$T:$T),0) | I3: =IF($A3="","",$F3-$H3)
G4: =IFERROR(SUMIF('Master FF&E Schedule'!$B:$B,$A4,'Master FF&E Schedule'!$P:$P),0) | H4: =IFERROR(SUMIF('Master FF&E Schedule'!$B:$B,$A4,'Master FF&E Schedule'!$T:$T),0) | I4: =IF($A4="","",$F4-$H4)
G5: =IFERROR(SUMIF('Master FF&E Schedule'!$B:$B,$A5,'Master FF&E Schedule'!$P:$P),0) | H5: =IFERROR(SUMIF('Master FF&E Schedule'!$B:$B,$A5,'Master FF&E Schedule'!$T:$T),0) | I5: =IF($A5="","",$F5-$H5)
G6: =IFERROR(SUMIF('Master FF&E Schedule'!$B:$B,$A6,'Master FF&E Schedule'!$P:$P),0) | H6: =IFERROR(SUMIF('Master FF&E Schedule'!$B:$B,$A6,'Master FF&E Schedule'!$T:$T),0) | I6: =IF($A6="","",$F6-$H6)
G7: =IFERROR(SUMIF('Master FF&E Schedule'!$B:$B,$A7,'Master FF&E Schedule'!$P:$P),0) | H7: =IFERROR(SUMIF('Master FF&E Schedule'!$B:$B,$A7,'Master FF&E Schedule'!$T:$T),0) | I7: =IF($A7="","",$F7-$H7)
G8: =IFERROR(SUMIF('Master FF&E Schedule'!$B:$B,$A8,'Master FF&E Schedule'!$P:$P),0) | H8: =IFERROR(SUMIF('Master FF&E Schedule'!$B:$B,$A8,'Master FF&E Schedule'!$T:$T),0) | I8: =IF($A8="","",$F8-$H8)
G9: =IFERROR(SUMIF('Master FF&E Schedule'!$B:$B,$A9,'Master FF&E Schedule'!$P:$P),0) | H9: =IFERROR(SUMIF('Master FF&E Schedule'!$B:$B,$A9,'Master FF&E Schedule'!$T:$T),0) | I9: =IF($A9="","",$F9-$H9)
G10: =IFERROR(SUMIF('Master FF&E Schedule'!$B:$B,$A10,'Master FF&E Schedule'!$P:$P),0) | H10: =IFERROR(SUMIF('Master FF&E Schedule'!$B:$B,$A10,'Master FF&E Schedule'!$T:$T),0) | I10: =IF($A10="","",$F10-$H10)
G11: =IFERROR(SUMIF('Master FF&E Schedule'!$B:$B,$A11,'Master FF&E Schedule'!$P:$P),0) | H11: =IFERROR(SUMIF('Master FF&E Schedule'!$B:$B,$A11,'Master FF&E Schedule'!$T:$T),0) | I11: =IF($A11="","",$F11-$H11)
G12: =IFERROR(SUMIF('Master FF&E Schedule'!$B:$B,$A12,'Master FF&E Schedule'!$P:$P),0) | H12: =IFERROR(SUMIF('Master FF&E Schedule'!$B:$B,$A12,'Master FF&E Schedule'!$T:$T),0) | I12: =IF($A12="","",$F12-$H12)
G13: =IFERROR(SUMIF('Master FF&E Schedule'!$B:$B,$A13,'Master FF&E Schedule'!$P:$P),0) | H13: =IFERROR(SUMIF('Master FF&E Schedule'!$B:$B,$A13,'Master FF&E Schedule'!$T:$T),0) | I13: =IF($A13="","",$F13-$H13)
... G251: =IFERROR(SUMIF('Master FF&E Schedule'!$B:$B,$A251,'Master FF&E Schedule'!$P:$P),0) | H251: =IFERROR(SUMIF('Master FF&E Schedule'!$B:$B,$A251,'Master FF&E Schedule'!$T:$T),0) | I251: =IF($A251="","",$F251-$H251)

Sheet Master FF&E Schedule
A1: Item ID | B1: Room | C1: Category | D1: Item name | E1: Description | F1: Quantity | G1: Dimensions | H1: Material | I1: Finish | J1: Color | K1: Vendor | L1: Brand | M1: Product link | N1: SKU/model number | O1: Unit cost | P1: Total cost | Q1: Tax | R1: Shipping | S1: Discount | T1: Final cost | U1: Lead time | V1: Order status | W1: Approval status | X1: Delivery status | Y1: Install status | Z1: Notes | AA1: Image link
P2: =IF($F2="","",$F2*$O2) | T2: =IF($P2="","",$P2+$Q2+$R2-$S2)
P3: =IF($F3="","",$F3*$O3) | T3: =IF($P3="","",$P3+$Q3+$R3-$S3)
P4: =IF($F4="","",$F4*$O4) | T4: =IF($P4="","",$P4+$Q4+$R4-$S4)
P5: =IF($F5="","",$F5*$O5) | T5: =IF($P5="","",$P5+$Q5+$R5-$S5)
P6: =IF($F6="","",$F6*$O6) | T6: =IF($P6="","",$P6+$Q6+$R6-$S6)
P7: =IF($F7="","",$F7*$O7) | T7: =IF($P7="","",$P7+$Q7+$R7-$S7)
P8: =IF($F8="","",$F8*$O8) | T8: =IF($P8="","",$P8+$Q8+$R8-$S8)
P9: =IF($F9="","",$F9*$O9) | T9: =IF($P9="","",$P9+$Q9+$R9-$S9)
P10: =IF($F10="","",$F10*$O10) | T10: =IF($P10="","",$P10+$Q10+$R10-$S10)
P11: =IF($F11="","",$F11*$O11) | T11: =IF($P11="","",$P11+$Q11+$R11-$S11)
P12: =IF($F12="","",$F12*$O12) | T12: =IF($P12="","",$P12+$Q12+$R12-$S12)
P13: =IF($F13="","",$F13*$O13) | T13: =IF($P13="","",$P13+$Q13+$R13-$S13)
... P251: =IF($F251="","",$F251*$O251) | T251: =IF($P251="","",$P251+$Q251+$R251-$S251)

Sheet Furniture Schedule
A1: Room | B1: Furniture item | C1: Dimensions | D1: Quantity | E1: Vendor | F1: Product link | G1: Fabric/material | H1: Finish | I1: Cost | J1: Approval status | K1: Order status | L1: Delivery date | M1: Install date

Sheet Fixtures Schedule
A1: Room | B1: Fixture type | C1: Item name | D1: Finish | E1: Size | F1: Vendor | G1: Model/SKU | H1: Quantity | I1: Unit cost | J1: Total cost | K1: Required rough-in date | L1: Order deadline | M1: Delivery date | N1: Installer notes
J2: =IF($H2="","",$H2*$I2)
J3: =IF($H3="","",$H3*$I3)
J4: =IF($H4="","",$H4*$I4)
J5: =IF($H5="","",$H5*$I5)
J6: =IF($H6="","",$H6*$I6)
J7: =IF($H7="","",$H7*$I7)
J8: =IF($H8="","",$H8*$I8)
J9: =IF($H9="","",$H9*$I9)
J10: =IF($H10="","",$H10*$I10)
J11: =IF($H11="","",$H11*$I11)
J12: =IF($H12="","",$H12*$I12)
J13: =IF($H13="","",$H13*$I13)
... J251: =IF($H251="","",$H251*$I251)

Sheet Finishes Schedule
A1: Room | B1: Surface/application | C1: Finish type | D1: Product name | E1: Color/finish | F1: Material | G1: Vendor | H1: Product link | I1: SKU | J1: Quantity needed | K1: Unit cost | L1: Total cost | M1: Sample ordered | N1: Sample approved | O1: Installer notes
L2: =IF($J2="","",$J2*$K2)
L3: =IF($J3="","",$J3*$K3)
L4: =IF($J4="","",$J4*$K4)
L5: =IF($J5="","",$J5*$K5)
L6: =IF($J6="","",$J6*$K6)
L7: =IF($J7="","",$J7*$K7)
L8: =IF($J8="","",$J8*$K8)
L9: =IF($J9="","",$J9*$K9)
L10: =IF($J10="","",$J10*$K10)
L11: =IF($J11="","",$J11*$K11)
L12: =IF($J12="","",$J12*$K12)
L13: =IF($J13="","",$J13*$K13)
... L251: =IF($J251="","",$J251*$K251)

Sheet Product Sourcing Tracker
A1: Room | B1: Item needed | C1: Option 1 link | D1: Option 1 price | E1: Option 2 link | F1: Option 2 price | G1: Option 3 link | H1: Option 3 price | I1: Preferred option | J1: Pros | K1: Cons | L1: Client feedback | M1: Final selection

Sheet Vendor & Supplier Database
A1: Vendor name | B1: Vendor type | C1: Contact person | D1: Email | E1: Phone | F1: Website | G1: Account number | H1: Trade discount % | I1: Lead time | J1: Shipping terms | K1: Return policy | L1: Notes

Sheet Budget Tracker
A1: Budget category | B1: Budgeted amount | C1: Estimated amount | D1: Actual amount | E1: Difference | F1: Paid amount | G1: Balance due | H1: Payment status | I1: Notes
A2: Furniture | E2: =IF($A2="","",$B2-$D2) | G2: =IF($A2="","",$D2-$F2)
A3: Lighting | E3: =IF($A3="","",$B3-$D3) | G3: =IF($A3="","",$D3-$F3)
A4: Rugs | E4: =IF($A4="","",$B4-$D4) | G4: =IF($A4="","",$D4-$F4)
A5: Decor | E5: =IF($A5="","",$B5-$D5) | G5: =IF($A5="","",$D5-$F5)
A6: Artwork | E6: =IF($A6="","",$B6-$D6) | G6: =IF($A6="","",$D6-$F6)
A7: Window treatments | E7: =IF($A7="","",$B7-$D7) | G7: =IF($A7="","",$D7-$F7)
A8: Flooring | E8: =IF($A8="","",$B8-$D8) | G8: =IF($A8="","",$D8-$F8)
A9: Paint/wallcovering | E9: =IF($A9="","",$B9-$D9) | G9: =IF($A9="","",$D9-$F9)
A10: Contractor labor | E10: =IF($A10="","",$B10-$D10) | G10: =IF($A10="","",$D10-$F10)
A11: Installation | E11: =IF($A11="","",$B11-$D11) | G11: =IF($A11="","",$D11-$F11)
A12: Shipping | E12: =IF($A12="","",$B12-$D12) | G12: =IF($A12="","",$D12-$F12)
A13: Taxes | E13: =IF($A13="","",$B13-$D13) | G13: =IF($A13="","",$D13-$F13)
... A15: Contingency | E15: =IF($A15="","",$B15-$D15) | G15: =IF($A15="","",$D15-$F15)
E16: =IF($A16="","",$B16-$D16) | G16: =IF($A16="","",$D16-$F16)
E17: =IF($A17="","",$B17-$D17) | G17: =IF($A17="","",$D17-$F17)
E18: =IF($A18="","",$B18-$D18) | G18: =IF($A18="","",$D18-$F18)
E19: =IF($A19="","",$B19-$D19) | G19: =IF($A19="","",$D19-$F19)
E20: =IF($A20="","",$B20-$D20) | G20: =IF($A20="","",$D20-$F20)
E21: =IF($A21="","",$B21-$D21) | G21: =IF($A21="","",$D21-$F21)
E22: =IF($A22="","",$B22-$D22) | G22: =IF($A22="","",$D22-$F22)
E23: =IF($A23="","",$B23-$D23) | G23: =IF($A23="","",$D23-$F23)
E24: =IF($A24="","",$B24-$D24) | G24: =IF($A24="","",$D24-$F24)
E25: =IF($A25="","",$B25-$D25) | G25: =IF($A25="","",$D25-$F25)
E26: =IF($A26="","",$B26-$D26) | G26: =IF($A26="","",$D26-$F26)
E27: =IF($A27="","",$B27-$D27) | G27: =IF($A27="","",$D27-$F27)
... E251: =IF($A251="","",$B251-$D251) | G251: =IF($A251="","",$D251-$F251)
A254: Total budget | B254: =SUM(B2:B251)
A255: Total estimated | B255: =SUM(C2:C251)
A256: Total actual | B256: =SUM(D2:D251)
A257: Over/under budget | B257: =B254-B256
A258: Total paid | B258: =SUM(F2:F251)
A259: Remaining balance | B259: =SUM(G2:G251)

Sheet Purchase Order Tracker
A1: PO number | B1: Vendor | C1: Room | D1: Item | E1: Quantity | F1: Order date | G1: Expected ship date | H1: Expected delivery date | I1: Actual delivery date | J1: Order status | K1: Tracking number | L1: Carrier | M1: Invoice number | N1: Amount | O1: Paid status | P1: Notes

Sheet Delivery & Installation
A1: Item | B1: Room | C1: Vendor | D1: Delivery address | E1: Expected delivery date | F1: Actual delivery date | G1: Delivery status | H1: Received by | I1: Damage check | J1: Damage notes | K1: Storage location | L1: Install date | M1: Installer | N1: Installation status | O1: Punch list notes

Sheet Client Approval Tracker
A1: Item/design decision | B1: Room | C1: Approval type | D1: Sent to client date | E1: Client response date | F1: Status | G1: Approved option | H1: Client comments | I1: Revision needed | J1: Final approval date

Sheet Project Timeline
A1: Phase | B1: Task | C1: Assigned to | D1: Start date | E1: Due date | F1: Completion date | G1: Status | H1: Priority | I1: Dependencies | J1: Notes | K1: Duration days | L1: Days overdue | M1: Gantt W1 | N1: Gantt W2 | O1: Gantt W3 | P1: Gantt W4 | Q1: Gantt W5 | R1: Gantt W6 | S1: Gantt W7 | T1: Gantt W8 | U1: Gantt W9 | V1: Gantt W10 | W1: Gantt W11 | X1: Gantt W12
K2: =IF(OR($D2="",$E2=""),"",$E2-$D2+1) | L2: =IF(AND($E2<TODAY(),$G2<>"Complete"),TODAY()-$E2,0) | M2: =IF(OR($D2="",$E2=""),"",IF(AND($D2<=IF('Client & Project Profile'!$B$10="",TODAY(),'Client & Project Profile'!$B$10)+0*7+6,$E2>=IF('Client & Project Profile'!$B$10="",TODAY(),'Client & Project Profile'!$B$10)+0*7),"■","")) | N2: =IF(OR($D2="",$E2=""),"",IF(AND($D2<=IF('Client & Project Profile'!$B$10="",TODAY(),'Client & Project Profile'!$B$10)+1*7+6,$E2>=IF('Client & Project Profile'!$B$10="",TODAY(),'Client & Project Profile'!$B$10)+1*7),"■","")) | O2: =IF(OR($D2="",$E2=""),"",IF(AND($D2<=IF('Client & Project Profile'!$B$10="",TODAY(),'Client & Project Profile'!$B$10)+2*7+6,$E2>=IF('Client & Project Profile'!$B$10="",TODAY(),'Client & Project Profile'!$B$10)+2*7),"■","")) | P2: =IF(OR($D2="",$E2=""),"",IF(AND($D2<=IF('Client & Project Profile'!$B$10="",TODAY(),'Client & Project Profile'!$B$10)+3*7+6,$E2>=IF('Client & Project Profile'!$B$10="",TODAY(),'Client & Project Profile'!$B$10)+3*7),"■","")) | Q2: =IF(OR($D2="",$E2=""),"",IF(AND($D2<=IF('Client & Project Profile'!$B$10="",TODAY(),'Client & Project Profile'!$B$10)+4*7+6,$E2>=IF('Client & Project Profile'!$B$10="",TODAY(),'Client & Project Profile'!$B$10)+4*7),"■","")) | R2: =IF(OR($D2="",$E2=""),"",IF(AND($D2<=IF('Client & Project Profile'!$B$10="",TODAY(),'Client & Project Profile'!$B$10)+5*7+6,$E2>=IF('Client & Project Profile'!$B$10="",TODAY(),'Client & Project Profile'!$B$10)+5*7),"■","")) | S2: =IF(OR($D2="",$E2=""),"",IF(AND($D2<=IF('Client & Project Profile'!$B$10="",TODAY(),'Client & Project Profile'!$B$10)+6*7+6,$E2>=IF('Client & Project Profile'!$B$10="",TODAY(),'Client & Project Profile'!$B$10)+6*7),"■","")) | T2: =IF(OR($D2="",$E2=""),"",IF(AND($D2<=IF('Client & Project Profile'!$B$10="",TODAY(),'Client & Project Profile'!$B$10)+7*7+6,$E2>=IF('Client & Project Profile'!$B$10="",TODAY(),'Client & Project Profile'!$B$10)+7*7),"■","")) | U2: =IF(OR($D2="",$E2=""),"",IF(AND($D2<=IF('Client & Project Profile'!$B$10="",TODAY(),'Client & Project Profile'!$B$10)+8*7+6,$E2>=IF('Client & Project Profile'!$B$10="",TODAY(),'Client & Project Profile'!$B$10)+8*7),"■","")) | V2: =IF(OR($D2="",$E2=""),"",IF(AND($D2<=IF('Client & Project Profile'!$B$10="",TODAY(),'Client & Project Profile'!$B$10)+9*7+6,$E2>=IF('Client & Project Profile'!$B$10="",TODAY(),'Client & Project Profile'!$B$10)+9*7),"■","")) | W2: =IF(OR($D2="",$E2=""),"",IF(AND($D2<=IF('Client & Project Profile'!$B$10="",TODAY(),'Client & Project Profile'!$B$10)+10*7+6,$E2>=IF('Client & Project Profile'!$B$10="",TODAY(),'Client & Project Profile'!$B$10)+10*7),"■","")) | X2: =IF(OR($D2="",$E2=""),"",IF(AND($D2<=IF('Client & Project Profile'!$B$10="",TODAY(),'Client & Project Profile'!$B$10)+11*7+6,$E2>=IF('Client & Project Profile'!$B$10="",TODAY(),'Client & Project Profile'!$B$10)+11*7),"■",""))
K3: =IF(OR($D3="",$E3=""),"",$E3-$D3+1) | L3: =IF(AND($E3<TODAY(),$G3<>"Complete"),TODAY()-$E3,0) | M3: =IF(OR($D3="",$E3=""),"",IF(AND($D3<=IF('Client & Project Profile'!$B$10="",TODAY(),'Client & Project Profile'!$B$10)+0*7+6,$E3>=IF('Client & Project Profile'!$B$10="",TODAY(),'Client & Project Profile'!$B$10)+0*7),"■","")) | N3: =IF(OR($D3="",$E3=""),"",IF(AND($D3<=IF('Client & Project Profile'!$B$10="",TODAY(),'Client & Project Profile'!$B$10)+1*7+6,$E3>=IF('Client & Project Profile'!$B$10="",TODAY(),'Client & Project Profile'!$B$10)+1*7),"■","")) | O3: =IF(OR($D3="",$E3=""),"",IF(AND($D3<=IF('Client & Project Profile'!$B$10="",TODAY(),'Client & Project Profile'!$B$10)+2*7+6,$E3>=IF('Client & Project Profile'!$B$10="",TODAY(),'Client & Project Profile'!$B$10)+2*7),"■","")) | P3: =IF(OR($D3="",$E3=""),"",IF(AND($D3<=IF('Client & Project Profile'!$B$10="",TODAY(),'Client & Project Profile'!$B$10)+3*7+6,$E3>=IF('Client & Project Profile'!$B$10="",TODAY(),'Client & Project Profile'!$B$10)+3*7),"■","")) | Q3: =IF(OR($D3="",$E3=""),"",IF(AND($D3<=IF('Client & Project Profile'!$B$10="",TODAY(),'Client & Project Profile'!$B$10)+4*7+6,$E3>=IF('Client & Project Profile'!$B$10="",TODAY(),'Client & Project Profile'!$B$10)+4*7),"■","")) | R3: =IF(OR($D3="",$E3=""),"",IF(AND($D3<=IF('Client & Project Profile'!$B$10="",TODAY(),'Client & Project Profile'!$B$10)+5*7+6,$E3>=IF('Client & Project Profile'!$B$10="",TODAY(),'Client & Project Profile'!$B$10)+5*7),"■","")) | S3: =IF(OR($D3="",$E3=""),"",IF(AND($D3<=IF('Client & Project Profile'!$B$10="",TODAY(),'Client & Project Profile'!$B$10)+6*7+6,$E3>=IF('Client & Project Profile'!$B$10="",TODAY(),'Client & Project Profile'!$B$10)+6*7),"■","")) | T3: =IF(OR($D3="",$E3=""),"",IF(AND($D3<=IF('Client & Project Profile'!$B$10="",TODAY(),'Client & Project Profile'!$B$10)+7*7+6,$E3>=IF('Client & Project Profile'!$B$10="",TODAY(),'Client & Project Profile'!$B$10)+7*7),"■","")) | U3: =IF(OR($D3="",$E3=""),"",IF(AND($D3<=IF('Client & Project Profile'!$B$10="",TODAY(),'Client & Project Profile'!$B$10)+8*7+6,$E3>=IF('Client & Project Profile'!$B$10="",TODAY(),'Client & Project Profile'!$B$10)+8*7),"■","")) | V3: =IF(OR($D3="",$E3=""),"",IF(AND($D3<=IF('Client & Project Profile'!$B$10="",TODAY(),'Client & Project Profile'!$B$10)+9*7+6,$E3>=IF('Client & Project Profile'!$B$10="",TODAY(),'Client & Project Profile'!$B$10)+9*7),"■","")) | W3: =IF(OR($D3="",$E3=""),"",IF(AND($D3<=IF('Client & Project Profile'!$B$10="",TODAY(),'Client & Project Profile'!$B$10)+10*7+6,$E3>=IF('Client & Project Profile'!$B$10="",TODAY(),'Client & Project Profile'!$B$10)+10*7),"■","")) | X3: =IF(OR($D3="",$E3=""),"",IF(AND($D3<=IF('Client & Project Profile'!$B$10="",TODAY(),'Client & Project Profile'!$B$10)+11*7+6,$E3>=IF('Client & Project Profile'!$B$10="",TODAY(),'Client & Project Profile'!$B$10)+11*7),"■",""))
K4: =IF(OR($D4="",$E4=""),"",$E4-$D4+1) | L4: =IF(AND($E4<TODAY(),$G4<>"Complete"),TODAY()-$E4,0) | M4: =IF(OR($D4="",$E4=""),"",IF(AND($D4<=IF('Client & Project Profile'!$B$10="",TODAY(),'Client & Project Profile'!$B$10)+0*7+6,$E4>=IF('Client & Project Profile'!$B$10="",TODAY(),'Client & Project Profile'!$B$10)+0*7),"■","")) | N4: =IF(OR($D4="",$E4=""),"",IF(AND($D4<=IF('Client & Project Profile'!$B$10="",TODAY(),'Client & Project Profile'!$B$10)+1*7+6,$E4>=IF('Client & Project Profile'!$B$10="",TODAY(),'Client & Project Profile'!$B$10)+1*7),"■","")) | O4: =IF(OR($D4="",$E4=""),"",IF(AND($D4<=IF('Client & Project Profile'!$B$10="",TODAY(),'Client & Project Profile'!$B$10)+2*7+6,$E4>=IF('Client & Project Profile'!$B$10="",TODAY(),'Client & Project Profile'!$B$10)+2*7),"■","")) | P4: =IF(OR($D4="",$E4=""),"",IF(AND($D4<=IF('Client & Project Profile'!$B$10="",TODAY(),'Client & Project Profile'!$B$10)+3*7+6,$E4>=IF('Client & Project Profile'!$B$10="",TODAY(),'Client & Project Profile'!$B$10)+3*7),"■","")) | Q4: =IF(OR($D4="",$E4=""),"",IF(AND($D4<=IF('Client & Project Profile'!$B$10="",TODAY(),'Client & Project Profile'!$B$10)+4*7+6,$E4>=IF('Client & Project Profile'!$B$10="",TODAY(),'Client & Project Profile'!$B$10)+4*7),"■","")) | R4: =IF(OR($D4="",$E4=""),"",IF(AND($D4<=IF('Client & Project Profile'!$B$10="",TODAY(),'Client & Project Profile'!$B$10)+5*7+6,$E4>=IF('Client & Project Profile'!$B$10="",TODAY(),'Client & Project Profile'!$B$10)+5*7),"■","")) | S4: =IF(OR($D4="",$E4=""),"",IF(AND($D4<=IF('Client & Project Profile'!$B$10="",TODAY(),'Client & Project Profile'!$B$10)+6*7+6,$E4>=IF('Client & Project Profile'!$B$10="",TODAY(),'Client & Project Profile'!$B$10)+6*7),"■","")) | T4: =IF(OR($D4="",$E4=""),"",IF(AND($D4<=IF('Client & Project Profile'!$B$10="",TODAY(),'Client & Project Profile'!$B$10)+7*7+6,$E4>=IF('Client & Project Profile'!$B$10="",TODAY(),'Client & Project Profile'!$B$10)+7*7),"■","")) | U4: =IF(OR($D4="",$E4=""),"",IF(AND($D4<=IF('Client & Project Profile'!$B$10="",TODAY(),'Client & Project Profile'!$B$10)+8*7+6,$E4>=IF('Client & Project Profile'!$B$10="",TODAY(),'Client & Project Profile'!$B$10)+8*7),"■","")) | V4: =IF(OR($D4="",$E4=""),"",IF(AND($D4<=IF('Client & Project Profile'!$B$10="",TODAY(),'Client & Project Profile'!$B$10)+9*7+6,$E4>=IF('Client & Project Profile'!$B$10="",TODAY(),'Client & Project Profile'!$B$10)+9*7),"■","")) | W4: =IF(OR($D4="",$E4=""),"",IF(AND($D4<=IF('Client & Project Profile'!$B$10="",TODAY(),'Client & Project Profile'!$B$10)+10*7+6,$E4>=IF('Client & Project Profile'!$B$10="",TODAY(),'Client & Project Profile'!$B$10)+10*7),"■","")) | X4: =IF(OR($D4="",$E4=""),"",IF(AND($D4<=IF('Client & Project Profile'!$B$10="",TODAY(),'Client & Project Profile'!$B$10)+11*7+6,$E4>=IF('Client & Project Profile'!$B$10="",TODAY(),'Client & Project Profile'!$B$10)+11*7),"■",""))
K5: =IF(OR($D5="",$E5=""),"",$E5-$D5+1) | L5: =IF(AND($E5<TODAY(),$G5<>"Complete"),TODAY()-$E5,0) | M5: =IF(OR($D5="",$E5=""),"",IF(AND($D5<=IF('Client & Project Profile'!$B$10="",TODAY(),'Client & Project Profile'!$B$10)+0*7+6,$E5>=IF('Client & Project Profile'!$B$10="",TODAY(),'Client & Project Profile'!$B$10)+0*7),"■","")) | N5: =IF(OR($D5="",$E5=""),"",IF(AND($D5<=IF('Client & Project Profile'!$B$10="",TODAY(),'Client & Project Profile'!$B$10)+1*7+6,$E5>=IF('Client & Project Profile'!$B$10="",TODAY(),'Client & Project Profile'!$B$10)+1*7),"■","")) | O5: =IF(OR($D5="",$E5=""),"",IF(AND($D5<=IF('Client & Project Profile'!$B$10="",TODAY(),'Client & Project Profile'!$B$10)+2*7+6,$E5>=IF('Client & Project Profile'!$B$10="",TODAY(),'Client & Project Profile'!$B$10)+2*7),"■","")) | P5: =IF(OR($D5="",$E5=""),"",IF(AND($D5<=IF('Client & Project Profile'!$B$10="",TODAY(),'Client & Project Profile'!$B$10)+3*7+6,$E5>=IF('Client & Project Profile'!$B$10="",TODAY(),'Client & Project Profile'!$B$10)+3*7),"■","")) | Q5: =IF(OR($D5="",$E5=""),"",IF(AND($D5<=IF('Client & Project Profile'!$B$10="",TODAY(),'Client & Project Profile'!$B$10)+4*7+6,$E5>=IF('Client & Project Profile'!$B$10="",TODAY(),'Client & Project Profile'!$B$10)+4*7),"■","")) | R5: =IF(OR($D5="",$E5=""),"",IF(AND($D5<=IF('Client & Project Profile'!$B$10="",TODAY(),'Client & Project Profile'!$B$10)+5*7+6,$E5>=IF('Client & Project Profile'!$B$10="",TODAY(),'Client & Project Profile'!$B$10)+5*7),"■","")) | S5: =IF(OR($D5="",$E5=""),"",IF(AND($D5<=IF('Client & Project Profile'!$B$10="",TODAY(),'Client & Project Profile'!$B$10)+6*7+6,$E5>=IF('Client & Project Profile'!$B$10="",TODAY(),'Client & Project Profile'!$B$10)+6*7),"■","")) | T5: =IF(OR($D5="",$E5=""),"",IF(AND($D5<=IF('Client & Project Profile'!$B$10="",TODAY(),'Client & Project Profile'!$B$10)+7*7+6,$E5>=IF('Client & Project Profile'!$B$10="",TODAY(),'Client & Project Profile'!$B$10)+7*7),"■","")) | U5: =IF(OR($D5="",$E5=""),"",IF(AND($D5<=IF('Client & Project Profile'!$B$10="",TODAY(),'Client & Project Profile'!$B$10)+8*7+6,$E5>=IF('Client & Project Profile'!$B$10="",TODAY(),'Client & Project Profile'!$B$10)+8*7),"■","")) | V5: =IF(OR($D5="",$E5=""),"",IF(AND($D5<=IF('Client & Project Profile'!$B$10="",TODAY(),'Client & Project Profile'!$B$10)+9*7+6,$E5>=IF('Client & Project Profile'!$B$10="",TODAY(),'Client & Project Profile'!$B$10)+9*7),"■","")) | W5: =IF(OR($D5="",$E5=""),"",IF(AND($D5<=IF('Client & Project Profile'!$B$10="",TODAY(),'Client & Project Profile'!$B$10)+10*7+6,$E5>=IF('Client & Project Profile'!$B$10="",TODAY(),'Client & Project Profile'!$B$10)+10*7),"■","")) | X5: =IF(OR($D5="",$E5=""),"",IF(AND($D5<=IF('Client & Project Profile'!$B$10="",TODAY(),'Client & Project Profile'!$B$10)+11*7+6,$E5>=IF('Client & Project Profile'!$B$10="",TODAY(),'Client & Project Profile'!$B$10)+11*7),"■",""))
K6: =IF(OR($D6="",$E6=""),"",$E6-$D6+1) | L6: =IF(AND($E6<TODAY(),$G6<>"Complete"),TODAY()-$E6,0) | M6: =IF(OR($D6="",$E6=""),"",IF(AND($D6<=IF('Client & Project Profile'!$B$10="",TODAY(),'Client & Project Profile'!$B$10)+0*7+6,$E6>=IF('Client & Project Profile'!$B$10="",TODAY(),'Client & Project Profile'!$B$10)+0*7),"■","")) | N6: =IF(OR($D6="",$E6=""),"",IF(AND($D6<=IF('Client & Project Profile'!$B$10="",TODAY(),'Client & Project Profile'!$B$10)+1*7+6,$E6>=IF('Client & Project Profile'!$B$10="",TODAY(),'Client & Project Profile'!$B$10)+1*7),"■","")) | O6: =IF(OR($D6="",$E6=""),"",IF(AND($D6<=IF('Client & Project Profile'!$B$10="",TODAY(),'Client & Project Profile'!$B$10)+2*7+6,$E6>=IF('Client & Project Profile'!$B$10="",TODAY(),'Client & Project Profile'!$B$10)+2*7),"■","")) | P6: =IF(OR($D6="",$E6=""),"",IF(AND($D6<=IF('Client & Project Profile'!$B$10="",TODAY(),'Client & Project Profile'!$B$10)+3*7+6,$E6>=IF('Client & Project Profile'!$B$10="",TODAY(),'Client & Project Profile'!$B$10)+3*7),"■","")) | Q6: =IF(OR($D6="",$E6=""),"",IF(AND($D6<=IF('Client & Project Profile'!$B$10="",TODAY(),'Client & Project Profile'!$B$10)+4*7+6,$E6>=IF('Client & Project Profile'!$B$10="",TODAY(),'Client & Project Profile'!$B$10)+4*7),"■","")) | R6: =IF(OR($D6="",$E6=""),"",IF(AND($D6<=IF('Client & Project Profile'!$B$10="",TODAY(),'Client & Project Profile'!$B$10)+5*7+6,$E6>=IF('Client & Project Profile'!$B$10="",TODAY(),'Client & Project Profile'!$B$10)+5*7),"■","")) | S6: =IF(OR($D6="",$E6=""),"",IF(AND($D6<=IF('Client & Project Profile'!$B$10="",TODAY(),'Client & Project Profile'!$B$10)+6*7+6,$E6>=IF('Client & Project Profile'!$B$10="",TODAY(),'Client & Project Profile'!$B$10)+6*7),"■","")) | T6: =IF(OR($D6="",$E6=""),"",IF(AND($D6<=IF('Client & Project Profile'!$B$10="",TODAY(),'Client & Project Profile'!$B$10)+7*7+6,$E6>=IF('Client & Project Profile'!$B$10="",TODAY(),'Client & Project Profile'!$B$10)+7*7),"■","")) | U6: =IF(OR($D6="",$E6=""),"",IF(AND($D6<=IF('Client & Project Profile'!$B$10="",TODAY(),'Client & Project Profile'!$B$10)+8*7+6,$E6>=IF('Client & Project Profile'!$B$10="",TODAY(),'Client & Project Profile'!$B$10)+8*7),"■","")) | V6: =IF(OR($D6="",$E6=""),"",IF(AND($D6<=IF('Client & Project Profile'!$B$10="",TODAY(),'Client & Project Profile'!$B$10)+9*7+6,$E6>=IF('Client & Project Profile'!$B$10="",TODAY(),'Client & Project Profile'!$B$10)+9*7),"■","")) | W6: =IF(OR($D6="",$E6=""),"",IF(AND($D6<=IF('Client & Project Profile'!$B$10="",TODAY(),'Client & Project Profile'!$B$10)+10*7+6,$E6>=IF('Client & Project Profile'!$B$10="",TODAY(),'Client & Project Profile'!$B$10)+10*7),"■","")) | X6: =IF(OR($D6="",$E6=""),"",IF(AND($D6<=IF('Client & Project Profile'!$B$10="",TODAY(),'Client & Project Profile'!$B$10)+11*7+6,$E6>=IF('Client & Project Profile'!$B$10="",TODAY(),'Client & Project Profile'!$B$10)+11*7),"■",""))
K7: =IF(OR($D7="",$E7=""),"",$E7-$D7+1) | L7: =IF(AND($E7<TODAY(),$G7<>"Complete"),TODAY()-$E7,0) | M7: =IF(OR($D7="",$E7=""),"",IF(AND($D7<=IF('Client & Project Profile'!$B$10="",TODAY(),'Client & Project Profile'!$B$10)+0*7+6,$E7>=IF('Client & Project Profile'!$B$10="",TODAY(),'Client & Project Profile'!$B$10)+0*7),"■","")) | N7: =IF(OR($D7="",$E7=""),"",IF(AND($D7<=IF('Client & Project Profile'!$B$10="",TODAY(),'Client & Project Profile'!$B$10)+1*7+6,$E7>=IF('Client & Project Profile'!$B$10="",TODAY(),'Client & Project Profile'!$B$10)+1*7),"■","")) | O7: =IF(OR($D7="",$E7=""),"",IF(AND($D7<=IF('Client & Project Profile'!$B$10="",TODAY(),'Client & Project Profile'!$B$10)+2*7+6,$E7>=IF('Client & Project Profile'!$B$10="",TODAY(),'Client & Project Profile'!$B$10)+2*7),"■","")) | P7: =IF(OR($D7="",$E7=""),"",IF(AND($D7<=IF('Client & Project Profile'!$B$10="",TODAY(),'Client & Project Profile'!$B$10)+3*7+6,$E7>=IF('Client & Project Profile'!$B$10="",TODAY(),'Client & Project Profile'!$B$10)+3*7),"■","")) | Q7: =IF(OR($D7="",$E7=""),"",IF(AND($D7<=IF('Client & Project Profile'!$B$10="",TODAY(),'Client & Project Profile'!$B$10)+4*7+6,$E7>=IF('Client & Project Profile'!$B$10="",TODAY(),'Client & Project Profile'!$B$10)+4*7),"■","")) | R7: =IF(OR($D7="",$E7=""),"",IF(AND($D7<=IF('Client & Project Profile'!$B$10="",TODAY(),'Client & Project Profile'!$B$10)+5*7+6,$E7>=IF('Client & Project Profile'!$B$10="",TODAY(),'Client & Project Profile'!$B$10)+5*7),"■","")) | S7: =IF(OR($D7="",$E7=""),"",IF(AND($D7<=IF('Client & Project Profile'!$B$10="",TODAY(),'Client & Project Profile'!$B$10)+6*7+6,$E7>=IF('Client & Project Profile'!$B$10="",TODAY(),'Client & Project Profile'!$B$10)+6*7),"■","")) | T7: =IF(OR($D7="",$E7=""),"",IF(AND($D7<=IF('Client & Project Profile'!$B$10="",TODAY(),'Client & Project Profile'!$B$10)+7*7+6,$E7>=IF('Client & Project Profile'!$B$10="",TODAY(),'Client & Project Profile'!$B$10)+7*7),"■","")) | U7: =IF(OR($D7="",$E7=""),"",IF(AND($D7<=IF('Client & Project Profile'!$B$10="",TODAY(),'Client & Project Profile'!$B$10)+8*7+6,$E7>=IF('Client & Project Profile'!$B$10="",TODAY(),'Client & Project Profile'!$B$10)+8*7),"■","")) | V7: =IF(OR($D7="",$E7=""),"",IF(AND($D7<=IF('Client & Project Profile'!$B$10="",TODAY(),'Client & Project Profile'!$B$10)+9*7+6,$E7>=IF('Client & Project Profile'!$B$10="",TODAY(),'Client & Project Profile'!$B$10)+9*7),"■","")) | W7: =IF(OR($D7="",$E7=""),"",IF(AND($D7<=IF('Client & Project Profile'!$B$10="",TODAY(),'Client & Project Profile'!$B$10)+10*7+6,$E7>=IF('Client & Project Profile'!$B$10="",TODAY(),'Client & Project Profile'!$B$10)+10*7),"■","")) | X7: =IF(OR($D7="",$E7=""),"",IF(AND($D7<=IF('Client & Project Profile'!$B$10="",TODAY(),'Client & Project Profile'!$B$10)+11*7+6,$E7>=IF('Client & Project Profile'!$B$10="",TODAY(),'Client & Project Profile'!$B$10)+11*7),"■",""))
K8: =IF(OR($D8="",$E8=""),"",$E8-$D8+1) | L8: =IF(AND($E8<TODAY(),$G8<>"Complete"),TODAY()-$E8,0) | M8: =IF(OR($D8="",$E8=""),"",IF(AND($D8<=IF('Client & Project Profile'!$B$10="",TODAY(),'Client & Project Profile'!$B$10)+0*7+6,$E8>=IF('Client & Project Profile'!$B$10="",TODAY(),'Client & Project Profile'!$B$10)+0*7),"■","")) | N8: =IF(OR($D8="",$E8=""),"",IF(AND($D8<=IF('Client & Project Profile'!$B$10="",TODAY(),'Client & Project Profile'!$B$10)+1*7+6,$E8>=IF('Client & Project Profile'!$B$10="",TODAY(),'Client & Project Profile'!$B$10)+1*7),"■","")) | O8: =IF(OR($D8="",$E8=""),"",IF(AND($D8<=IF('Client & Project Profile'!$B$10="",TODAY(),'Client & Project Profile'!$B$10)+2*7+6,$E8>=IF('Client & Project Profile'!$B$10="",TODAY(),'Client & Project Profile'!$B$10)+2*7),"■","")) | P8: =IF(OR($D8="",$E8=""),"",IF(AND($D8<=IF('Client & Project Profile'!$B$10="",TODAY(),'Client & Project Profile'!$B$10)+3*7+6,$E8>=IF('Client & Project Profile'!$B$10="",TODAY(),'Client & Project Profile'!$B$10)+3*7),"■","")) | Q8: =IF(OR($D8="",$E8=""),"",IF(AND($D8<=IF('Client & Project Profile'!$B$10="",TODAY(),'Client & Project Profile'!$B$10)+4*7+6,$E8>=IF('Client & Project Profile'!$B$10="",TODAY(),'Client & Project Profile'!$B$10)+4*7),"■","")) | R8: =IF(OR($D8="",$E8=""),"",IF(AND($D8<=IF('Client & Project Profile'!$B$10="",TODAY(),'Client & Project Profile'!$B$10)+5*7+6,$E8>=IF('Client & Project Profile'!$B$10="",TODAY(),'Client & Project Profile'!$B$10)+5*7),"■","")) | S8: =IF(OR($D8="",$E8=""),"",IF(AND($D8<=IF('Client & Project Profile'!$B$10="",TODAY(),'Client & Project Profile'!$B$10)+6*7+6,$E8>=IF('Client & Project Profile'!$B$10="",TODAY(),'Client & Project Profile'!$B$10)+6*7),"■","")) | T8: =IF(OR($D8="",$E8=""),"",IF(AND($D8<=IF('Client & Project Profile'!$B$10="",TODAY(),'Client & Project Profile'!$B$10)+7*7+6,$E8>=IF('Client & Project Profile'!$B$10="",TODAY(),'Client & Project Profile'!$B$10)+7*7),"■","")) | U8: =IF(OR($D8="",$E8=""),"",IF(AND($D8<=IF('Client & Project Profile'!$B$10="",TODAY(),'Client & Project Profile'!$B$10)+8*7+6,$E8>=IF('Client & Project Profile'!$B$10="",TODAY(),'Client & Project Profile'!$B$10)+8*7),"■","")) | V8: =IF(OR($D8="",$E8=""),"",IF(AND($D8<=IF('Client & Project Profile'!$B$10="",TODAY(),'Client & Project Profile'!$B$10)+9*7+6,$E8>=IF('Client & Project Profile'!$B$10="",TODAY(),'Client & Project Profile'!$B$10)+9*7),"■","")) | W8: =IF(OR($D8="",$E8=""),"",IF(AND($D8<=IF('Client & Project Profile'!$B$10="",TODAY(),'Client & Project Profile'!$B$10)+10*7+6,$E8>=IF('Client & Project Profile'!$B$10="",TODAY(),'Client & Project Profile'!$B$10)+10*7),"■","")) | X8: =IF(OR($D8="",$E8=""),"",IF(AND($D8<=IF('Client & Project Profile'!$B$10="",TODAY(),'Client & Project Profile'!$B$10)+11*7+6,$E8>=IF('Client & Project Profile'!$B$10="",TODAY(),'Client & Project Profile'!$B$10)+11*7),"■",""))
K9: =IF(OR($D9="",$E9=""),"",$E9-$D9+1) | L9: =IF(AND($E9<TODAY(),$G9<>"Complete"),TODAY()-$E9,0) | M9: =IF(OR($D9="",$E9=""),"",IF(AND($D9<=IF('Client & Project Profile'!$B$10="",TODAY(),'Client & Project Profile'!$B$10)+0*7+6,$E9>=IF('Client & Project Profile'!$B$10="",TODAY(),'Client & Project Profile'!$B$10)+0*7),"■","")) | N9: =IF(OR($D9="",$E9=""),"",IF(AND($D9<=IF('Client & Project Profile'!$B$10="",TODAY(),'Client & Project Profile'!$B$10)+1*7+6,$E9>=IF('Client & Project Profile'!$B$10="",TODAY(),'Client & Project Profile'!$B$10)+1*7),"■","")) | O9: =IF(OR($D9="",$E9=""),"",IF(AND($D9<=IF('Client & Project Profile'!$B$10="",TODAY(),'Client & Project Profile'!$B$10)+2*7+6,$E9>=IF('Client & Project Profile'!$B$10="",TODAY(),'Client & Project Profile'!$B$10)+2*7),"■","")) | P9: =IF(OR($D9="",$E9=""),"",IF(AND($D9<=IF('Client & Project Profile'!$B$10="",TODAY(),'Client & Project Profile'!$B$10)+3*7+6,$E9>=IF('Client & Project Profile'!$B$10="",TODAY(),'Client & Project Profile'!$B$10)+3*7),"■","")) | Q9: =IF(OR($D9="",$E9=""),"",IF(AND($D9<=IF('Client & Project Profile'!$B$10="",TODAY(),'Client & Project Profile'!$B$10)+4*7+6,$E9>=IF('Client & Project Profile'!$B$10="",TODAY(),'Client & Project Profile'!$B$10)+4*7),"■","")) | R9: =IF(OR($D9="",$E9=""),"",IF(AND($D9<=IF('Client & Project Profile'!$B$10="",TODAY(),'Client & Project Profile'!$B$10)+5*7+6,$E9>=IF('Client & Project Profile'!$B$10="",TODAY(),'Client & Project Profile'!$B$10)+5*7),"■","")) | S9: =IF(OR($D9="",$E9=""),"",IF(AND($D9<=IF('Client & Project Profile'!$B$10="",TODAY(),'Client & Project Profile'!$B$10)+6*7+6,$E9>=IF('Client & Project Profile'!$B$10="",TODAY(),'Client & Project Profile'!$B$10)+6*7),"■","")) | T9: =IF(OR($D9="",$E9=""),"",IF(AND($D9<=IF('Client & Project Profile'!$B$10="",TODAY(),'Client & Project Profile'!$B$10)+7*7+6,$E9>=IF('Client & Project Profile'!$B$10="",TODAY(),'Client & Project Profile'!$B$10)+7*7),"■","")) | U9: =IF(OR($D9="",$E9=""),"",IF(AND($D9<=IF('Client & Project Profile'!$B$10="",TODAY(),'Client & Project Profile'!$B$10)+8*7+6,$E9>=IF('Client & Project Profile'!$B$10="",TODAY(),'Client & Project Profile'!$B$10)+8*7),"■","")) | V9: =IF(OR($D9="",$E9=""),"",IF(AND($D9<=IF('Client & Project Profile'!$B$10="",TODAY(),'Client & Project Profile'!$B$10)+9*7+6,$E9>=IF('Client & Project Profile'!$B$10="",TODAY(),'Client & Project Profile'!$B$10)+9*7),"■","")) | W9: =IF(OR($D9="",$E9=""),"",IF(AND($D9<=IF('Client & Project Profile'!$B$10="",TODAY(),'Client & Project Profile'!$B$10)+10*7+6,$E9>=IF('Client & Project Profile'!$B$10="",TODAY(),'Client & Project Profile'!$B$10)+10*7),"■","")) | X9: =IF(OR($D9="",$E9=""),"",IF(AND($D9<=IF('Client & Project Profile'!$B$10="",TODAY(),'Client & Project Profile'!$B$10)+11*7+6,$E9>=IF('Client & Project Profile'!$B$10="",TODAY(),'Client & Project Profile'!$B$10)+11*7),"■",""))
K10: =IF(OR($D10="",$E10=""),"",$E10-$D10+1) | L10: =IF(AND($E10<TODAY(),$G10<>"Complete"),TODAY()-$E10,0) | M10: =IF(OR($D10="",$E10=""),"",IF(AND($D10<=IF('Client & Project Profile'!$B$10="",TODAY(),'Client & Project Profile'!$B$10)+0*7+6,$E10>=IF('Client & Project Profile'!$B$10="",TODAY(),'Client & Project Profile'!$B$10)+0*7),"■","")) | N10: =IF(OR($D10="",$E10=""),"",IF(AND($D10<=IF('Client & Project Profile'!$B$10="",TODAY(),'Client & Project Profile'!$B$10)+1*7+6,$E10>=IF('Client & Project Profile'!$B$10="",TODAY(),'Client & Project Profile'!$B$10)+1*7),"■","")) | O10: =IF(OR($D10="",$E10=""),"",IF(AND($D10<=IF('Client & Project Profile'!$B$10="",TODAY(),'Client & Project Profile'!$B$10)+2*7+6,$E10>=IF('Client & Project Profile'!$B$10="",TODAY(),'Client & Project Profile'!$B$10)+2*7),"■","")) | P10: =IF(OR($D10="",$E10=""),"",IF(AND($D10<=IF('Client & Project Profile'!$B$10="",TODAY(),'Client & Project Profile'!$B$10)+3*7+6,$E10>=IF('Client & Project Profile'!$B$10="",TODAY(),'Client & Project Profile'!$B$10)+3*7),"■","")) | Q10: =IF(OR($D10="",$E10=""),"",IF(AND($D10<=IF('Client & Project Profile'!$B$10="",TODAY(),'Client & Project Profile'!$B$10)+4*7+6,$E10>=IF('Client & Project Profile'!$B$10="",TODAY(),'Client & Project Profile'!$B$10)+4*7),"■","")) | R10: =IF(OR($D10="",$E10=""),"",IF(AND($D10<=IF('Client & Project Profile'!$B$10="",TODAY(),'Client & Project Profile'!$B$10)+5*7+6,$E10>=IF('Client & Project Profile'!$B$10="",TODAY(),'Client & Project Profile'!$B$10)+5*7),"■","")) | S10: =IF(OR($D10="",$E10=""),"",IF(AND($D10<=IF('Client & Project Profile'!$B$10="",TODAY(),'Client & Project Profile'!$B$10)+6*7+6,$E10>=IF('Client & Project Profile'!$B$10="",TODAY(),'Client & Project Profile'!$B$10)+6*7),"■","")) | T10: =IF(OR($D10="",$E10=""),"",IF(AND($D10<=IF('Client & Project Profile'!$B$10="",TODAY(),'Client & Project Profile'!$B$10)+7*7+6,$E10>=IF('Client & Project Profile'!$B$10="",TODAY(),'Client & Project Profile'!$B$10)+7*7),"■","")) | U10: =IF(OR($D10="",$E10=""),"",IF(AND($D10<=IF('Client & Project Profile'!$B$10="",TODAY(),'Client & Project Profile'!$B$10)+8*7+6,$E10>=IF('Client & Project Profile'!$B$10="",TODAY(),'Client & Project Profile'!$B$10)+8*7),"■","")) | V10: =IF(OR($D10="",$E10=""),"",IF(AND($D10<=IF('Client & Project Profile'!$B$10="",TODAY(),'Client & Project Profile'!$B$10)+9*7+6,$E10>=IF('Client & Project Profile'!$B$10="",TODAY(),'Client & Project Profile'!$B$10)+9*7),"■","")) | W10: =IF(OR($D10="",$E10=""),"",IF(AND($D10<=IF('Client & Project Profile'!$B$10="",TODAY(),'Client & Project Profile'!$B$10)+10*7+6,$E10>=IF('Client & Project Profile'!$B$10="",TODAY(),'Client & Project Profile'!$B$10)+10*7),"■","")) | X10: =IF(OR($D10="",$E10=""),"",IF(AND($D10<=IF('Client & Project Profile'!$B$10="",TODAY(),'Client & Project Profile'!$B$10)+11*7+6,$E10>=IF('Client & Project Profile'!$B$10="",TODAY(),'Client & Project Profile'!$B$10)+11*7),"■",""))
K11: =IF(OR($D11="",$E11=""),"",$E11-$D11+1) | L11: =IF(AND($E11<TODAY(),$G11<>"Complete"),TODAY()-$E11,0) | M11: =IF(OR($D11="",$E11=""),"",IF(AND($D11<=IF('Client & Project Profile'!$B$10="",TODAY(),'Client & Project Profile'!$B$10)+0*7+6,$E11>=IF('Client & Project Profile'!$B$10="",TODAY(),'Client & Project Profile'!$B$10)+0*7),"■","")) | N11: =IF(OR($D11="",$E11=""),"",IF(AND($D11<=IF('Client & Project Profile'!$B$10="",TODAY(),'Client & Project Profile'!$B$10)+1*7+6,$E11>=IF('Client & Project Profile'!$B$10="",TODAY(),'Client & Project Profile'!$B$10)+1*7),"■","")) | O11: =IF(OR($D11="",$E11=""),"",IF(AND($D11<=IF('Client & Project Profile'!$B$10="",TODAY(),'Client & Project Profile'!$B$10)+2*7+6,$E11>=IF('Client & Project Profile'!$B$10="",TODAY(),'Client & Project Profile'!$B$10)+2*7),"■","")) | P11: =IF(OR($D11="",$E11=""),"",IF(AND($D11<=IF('Client & Project Profile'!$B$10="",TODAY(),'Client & Project Profile'!$B$10)+3*7+6,$E11>=IF('Client & Project Profile'!$B$10="",TODAY(),'Client & Project Profile'!$B$10)+3*7),"■","")) | Q11: =IF(OR($D11="",$E11=""),"",IF(AND($D11<=IF('Client & Project Profile'!$B$10="",TODAY(),'Client & Project Profile'!$B$10)+4*7+6,$E11>=IF('Client & Project Profile'!$B$10="",TODAY(),'Client & Project Profile'!$B$10)+4*7),"■","")) | R11: =IF(OR($D11="",$E11=""),"",IF(AND($D11<=IF('Client & Project Profile'!$B$10="",TODAY(),'Client & Project Profile'!$B$10)+5*7+6,$E11>=IF('Client & Project Profile'!$B$10="",TODAY(),'Client & Project Profile'!$B$10)+5*7),"■","")) | S11: =IF(OR($D11="",$E11=""),"",IF(AND($D11<=IF('Client & Project Profile'!$B$10="",TODAY(),'Client & Project Profile'!$B$10)+6*7+6,$E11>=IF('Client & Project Profile'!$B$10="",TODAY(),'Client & Project Profile'!$B$10)+6*7),"■","")) | T11: =IF(OR($D11="",$E11=""),"",IF(AND($D11<=IF('Client & Project Profile'!$B$10="",TODAY(),'Client & Project Profile'!$B$10)+7*7+6,$E11>=IF('Client & Project Profile'!$B$10="",TODAY(),'Client & Project Profile'!$B$10)+7*7),"■","")) | U11: =IF(OR($D11="",$E11=""),"",IF(AND($D11<=IF('Client & Project Profile'!$B$10="",TODAY(),'Client & Project Profile'!$B$10)+8*7+6,$E11>=IF('Client & Project Profile'!$B$10="",TODAY(),'Client & Project Profile'!$B$10)+8*7),"■","")) | V11: =IF(OR($D11="",$E11=""),"",IF(AND($D11<=IF('Client & Project Profile'!$B$10="",TODAY(),'Client & Project Profile'!$B$10)+9*7+6,$E11>=IF('Client & Project Profile'!$B$10="",TODAY(),'Client & Project Profile'!$B$10)+9*7),"■","")) | W11: =IF(OR($D11="",$E11=""),"",IF(AND($D11<=IF('Client & Project Profile'!$B$10="",TODAY(),'Client & Project Profile'!$B$10)+10*7+6,$E11>=IF('Client & Project Profile'!$B$10="",TODAY(),'Client & Project Profile'!$B$10)+10*7),"■","")) | X11: =IF(OR($D11="",$E11=""),"",IF(AND($D11<=IF('Client & Project Profile'!$B$10="",TODAY(),'Client & Project Profile'!$B$10)+11*7+6,$E11>=IF('Client & Project Profile'!$B$10="",TODAY(),'Client & Project Profile'!$B$10)+11*7),"■",""))
K12: =IF(OR($D12="",$E12=""),"",$E12-$D12+1) | L12: =IF(AND($E12<TODAY(),$G12<>"Complete"),TODAY()-$E12,0) | M12: =IF(OR($D12="",$E12=""),"",IF(AND($D12<=IF('Client & Project Profile'!$B$10="",TODAY(),'Client & Project Profile'!$B$10)+0*7+6,$E12>=IF('Client & Project Profile'!$B$10="",TODAY(),'Client & Project Profile'!$B$10)+0*7),"■","")) | N12: =IF(OR($D12="",$E12=""),"",IF(AND($D12<=IF('Client & Project Profile'!$B$10="",TODAY(),'Client & Project Profile'!$B$10)+1*7+6,$E12>=IF('Client & Project Profile'!$B$10="",TODAY(),'Client & Project Profile'!$B$10)+1*7),"■","")) | O12: =IF(OR($D12="",$E12=""),"",IF(AND($D12<=IF('Client & Project Profile'!$B$10="",TODAY(),'Client & Project Profile'!$B$10)+2*7+6,$E12>=IF('Client & Project Profile'!$B$10="",TODAY(),'Client & Project Profile'!$B$10)+2*7),"■","")) | P12: =IF(OR($D12="",$E12=""),"",IF(AND($D12<=IF('Client & Project Profile'!$B$10="",TODAY(),'Client & Project Profile'!$B$10)+3*7+6,$E12>=IF('Client & Project Profile'!$B$10="",TODAY(),'Client & Project Profile'!$B$10)+3*7),"■","")) | Q12: =IF(OR($D12="",$E12=""),"",IF(AND($D12<=IF('Client & Project Profile'!$B$10="",TODAY(),'Client & Project Profile'!$B$10)+4*7+6,$E12>=IF('Client & Project Profile'!$B$10="",TODAY(),'Client & Project Profile'!$B$10)+4*7),"■","")) | R12: =IF(OR($D12="",$E12=""),"",IF(AND($D12<=IF('Client & Project Profile'!$B$10="",TODAY(),'Client & Project Profile'!$B$10)+5*7+6,$E12>=IF('Client & Project Profile'!$B$10="",TODAY(),'Client & Project Profile'!$B$10)+5*7),"■","")) | S12: =IF(OR($D12="",$E12=""),"",IF(AND($D12<=IF('Client & Project Profile'!$B$10="",TODAY(),'Client & Project Profile'!$B$10)+6*7+6,$E12>=IF('Client & Project Profile'!$B$10="",TODAY(),'Client & Project Profile'!$B$10)+6*7),"■","")) | T12: =IF(OR($D12="",$E12=""),"",IF(AND($D12<=IF('Client & Project Profile'!$B$10="",TODAY(),'Client & Project Profile'!$B$10)+7*7+6,$E12>=IF('Client & Project Profile'!$B$10="",TODAY(),'Client & Project Profile'!$B$10)+7*7),"■","")) | U12: =IF(OR($D12="",$E12=""),"",IF(AND($D12<=IF('Client & Project Profile'!$B$10="",TODAY(),'Client & Project Profile'!$B$10)+8*7+6,$E12>=IF('Client & Project Profile'!$B$10="",TODAY(),'Client & Project Profile'!$B$10)+8*7),"■","")) | V12: =IF(OR($D12="",$E12=""),"",IF(AND($D12<=IF('Client & Project Profile'!$B$10="",TODAY(),'Client & Project Profile'!$B$10)+9*7+6,$E12>=IF('Client & Project Profile'!$B$10="",TODAY(),'Client & Project Profile'!$B$10)+9*7),"■","")) | W12: =IF(OR($D12="",$E12=""),"",IF(AND($D12<=IF('Client & Project Profile'!$B$10="",TODAY(),'Client & Project Profile'!$B$10)+10*7+6,$E12>=IF('Client & Project Profile'!$B$10="",TODAY(),'Client & Project Profile'!$B$10)+10*7),"■","")) | X12: =IF(OR($D12="",$E12=""),"",IF(AND($D12<=IF('Client & Project Profile'!$B$10="",TODAY(),'Client & Project Profile'!$B$10)+11*7+6,$E12>=IF('Client & Project Profile'!$B$10="",TODAY(),'Client & Project Profile'!$B$10)+11*7),"■",""))
K13: =IF(OR($D13="",$E13=""),"",$E13-$D13+1) | L13: =IF(AND($E13<TODAY(),$G13<>"Complete"),TODAY()-$E13,0) | M13: =IF(OR($D13="",$E13=""),"",IF(AND($D13<=IF('Client & Project Profile'!$B$10="",TODAY(),'Client & Project Profile'!$B$10)+0*7+6,$E13>=IF('Client & Project Profile'!$B$10="",TODAY(),'Client & Project Profile'!$B$10)+0*7),"■","")) | N13: =IF(OR($D13="",$E13=""),"",IF(AND($D13<=IF('Client & Project Profile'!$B$10="",TODAY(),'Client & Project Profile'!$B$10)+1*7+6,$E13>=IF('Client & Project Profile'!$B$10="",TODAY(),'Client & Project Profile'!$B$10)+1*7),"■","")) | O13: =IF(OR($D13="",$E13=""),"",IF(AND($D13<=IF('Client & Project Profile'!$B$10="",TODAY(),'Client & Project Profile'!$B$10)+2*7+6,$E13>=IF('Client & Project Profile'!$B$10="",TODAY(),'Client & Project Profile'!$B$10)+2*7),"■","")) | P13: =IF(OR($D13="",$E13=""),"",IF(AND($D13<=IF('Client & Project Profile'!$B$10="",TODAY(),'Client & Project Profile'!$B$10)+3*7+6,$E13>=IF('Client & Project Profile'!$B$10="",TODAY(),'Client & Project Profile'!$B$10)+3*7),"■","")) | Q13: =IF(OR($D13="",$E13=""),"",IF(AND($D13<=IF('Client & Project Profile'!$B$10="",TODAY(),'Client & Project Profile'!$B$10)+4*7+6,$E13>=IF('Client & Project Profile'!$B$10="",TODAY(),'Client & Project Profile'!$B$10)+4*7),"■","")) | R13: =IF(OR($D13="",$E13=""),"",IF(AND($D13<=IF('Client & Project Profile'!$B$10="",TODAY(),'Client & Project Profile'!$B$10)+5*7+6,$E13>=IF('Client & Project Profile'!$B$10="",TODAY(),'Client & Project Profile'!$B$10)+5*7),"■","")) | S13: =IF(OR($D13="",$E13=""),"",IF(AND($D13<=IF('Client & Project Profile'!$B$10="",TODAY(),'Client & Project Profile'!$B$10)+6*7+6,$E13>=IF('Client & Project Profile'!$B$10="",TODAY(),'Client & Project Profile'!$B$10)+6*7),"■","")) | T13: =IF(OR($D13="",$E13=""),"",IF(AND($D13<=IF('Client & Project Profile'!$B$10="",TODAY(),'Client & Project Profile'!$B$10)+7*7+6,$E13>=IF('Client & Project Profile'!$B$10="",TODAY(),'Client & Project Profile'!$B$10)+7*7),"■","")) | U13: =IF(OR($D13="",$E13=""),"",IF(AND($D13<=IF('Client & Project Profile'!$B$10="",TODAY(),'Client & Project Profile'!$B$10)+8*7+6,$E13>=IF('Client & Project Profile'!$B$10="",TODAY(),'Client & Project Profile'!$B$10)+8*7),"■","")) | V13: =IF(OR($D13="",$E13=""),"",IF(AND($D13<=IF('Client & Project Profile'!$B$10="",TODAY(),'Client & Project Profile'!$B$10)+9*7+6,$E13>=IF('Client & Project Profile'!$B$10="",TODAY(),'Client & Project Profile'!$B$10)+9*7),"■","")) | W13: =IF(OR($D13="",$E13=""),"",IF(AND($D13<=IF('Client & Project Profile'!$B$10="",TODAY(),'Client & Project Profile'!$B$10)+10*7+6,$E13>=IF('Client & Project Profile'!$B$10="",TODAY(),'Client & Project Profile'!$B$10)+10*7),"■","")) | X13: =IF(OR($D13="",$E13=""),"",IF(AND($D13<=IF('Client & Project Profile'!$B$10="",TODAY(),'Client & Project Profile'!$B$10)+11*7+6,$E13>=IF('Client & Project Profile'!$B$10="",TODAY(),'Client & Project Profile'!$B$10)+11*7),"■",""))
... K251: =IF(OR($D251="",$E251=""),"",$E251-$D251+1) | L251: =IF(AND($E251<TODAY(),$G251<>"Complete"),TODAY()-$E251,0) | M251: =IF(OR($D251="",$E251=""),"",IF(AND($D251<=IF('Client & Project Profile'!$B$10="",TODAY(),'Client & Project Profile'!$B$10)+0*7+6,$E251>=IF('Client & Project Profile'!$B$10="",TODAY(),'Client & Project Profile'!$B$10)+0*7),"■","")) | N251: =IF(OR($D251="",$E251=""),"",IF(AND($D251<=IF('Client & Project Profile'!$B$10="",TODAY(),'Client & Project Profile'!$B$10)+1*7+6,$E251>=IF('Client & Project Profile'!$B$10="",TODAY(),'Client & Project Profile'!$B$10)+1*7),"■","")) | O251: =IF(OR($D251="",$E251=""),"",IF(AND($D251<=IF('Client & Project Profile'!$B$10="",TODAY(),'Client & Project Profile'!$B$10)+2*7+6,$E251>=IF('Client & Project Profile'!$B$10="",TODAY(),'Client & Project Profile'!$B$10)+2*7),"■","")) | P251: =IF(OR($D251="",$E251=""),"",IF(AND($D251<=IF('Client & Project Profile'!$B$10="",TODAY(),'Client & Project Profile'!$B$10)+3*7+6,$E251>=IF('Client & Project Profile'!$B$10="",TODAY(),'Client & Project Profile'!$B$10)+3*7),"■","")) | Q251: =IF(OR($D251="",$E251=""),"",IF(AND($D251<=IF('Client & Project Profile'!$B$10="",TODAY(),'Client & Project Profile'!$B$10)+4*7+6,$E251>=IF('Client & Project Profile'!$B$10="",TODAY(),'Client & Project Profile'!$B$10)+4*7),"■","")) | R251: =IF(OR($D251="",$E251=""),"",IF(AND($D251<=IF('Client & Project Profile'!$B$10="",TODAY(),'Client & Project Profile'!$B$10)+5*7+6,$E251>=IF('Client & Project Profile'!$B$10="",TODAY(),'Client & Project Profile'!$B$10)+5*7),"■","")) | S251: =IF(OR($D251="",$E251=""),"",IF(AND($D251<=IF('Client & Project Profile'!$B$10="",TODAY(),'Client & Project Profile'!$B$10)+6*7+6,$E251>=IF('Client & Project Profile'!$B$10="",TODAY(),'Client & Project Profile'!$B$10)+6*7),"■","")) | T251: =IF(OR($D251="",$E251=""),"",IF(AND($D251<=IF('Client & Project Profile'!$B$10="",TODAY(),'Client & Project Profile'!$B$10)+7*7+6,$E251>=IF('Client & Project Profile'!$B$10="",TODAY(),'Client & Project Profile'!$B$10)+7*7),"■","")) | U251: =IF(OR($D251="",$E251=""),"",IF(AND($D251<=IF('Client & Project Profile'!$B$10="",TODAY(),'Client & Project Profile'!$B$10)+8*7+6,$E251>=IF('Client & Project Profile'!$B$10="",TODAY(),'Client & Project Profile'!$B$10)+8*7),"■","")) | V251: =IF(OR($D251="",$E251=""),"",IF(AND($D251<=IF('Client & Project Profile'!$B$10="",TODAY(),'Client & Project Profile'!$B$10)+9*7+6,$E251>=IF('Client & Project Profile'!$B$10="",TODAY(),'Client & Project Profile'!$B$10)+9*7),"■","")) | W251: =IF(OR($D251="",$E251=""),"",IF(AND($D251<=IF('Client & Project Profile'!$B$10="",TODAY(),'Client & Project Profile'!$B$10)+10*7+6,$E251>=IF('Client & Project Profile'!$B$10="",TODAY(),'Client & Project Profile'!$B$10)+10*7),"■","")) | X251: =IF(OR($D251="",$E251=""),"",IF(AND($D251<=IF('Client & Project Profile'!$B$10="",TODAY(),'Client & Project Profile'!$B$10)+11*7+6,$E251>=IF('Client & Project Profile'!$B$10="",TODAY(),'Client & Project Profile'!$B$10)+11*7),"■",""))

Sheet Task & To-Do List
A1: Task | B1: Room | C1: Category | D1: Assigned to | E1: Priority | F1: Due date | G1: Status | H1: Notes | I1: Days overdue
I2: =IF(AND($F2<TODAY(),$G2<>"Complete"),TODAY()-$F2,0)
I3: =IF(AND($F3<TODAY(),$G3<>"Complete"),TODAY()-$F3,0)
I4: =IF(AND($F4<TODAY(),$G4<>"Complete"),TODAY()-$F4,0)
I5: =IF(AND($F5<TODAY(),$G5<>"Complete"),TODAY()-$F5,0)
I6: =IF(AND($F6<TODAY(),$G6<>"Complete"),TODAY()-$F6,0)
I7: =IF(AND($F7<TODAY(),$G7<>"Complete"),TODAY()-$F7,0)
I8: =IF(AND($F8<TODAY(),$G8<>"Complete"),TODAY()-$F8,0)
I9: =IF(AND($F9<TODAY(),$G9<>"Complete"),TODAY()-$F9,0)
I10: =IF(AND($F10<TODAY(),$G10<>"Complete"),TODAY()-$F10,0)
I11: =IF(AND($F11<TODAY(),$G11<>"Complete"),TODAY()-$F11,0)
I12: =IF(AND($F12<TODAY(),$G12<>"Complete"),TODAY()-$F12,0)
I13: =IF(AND($F13<TODAY(),$G13<>"Complete"),TODAY()-$F13,0)
... I251: =IF(AND($F251<TODAY(),$G251<>"Complete"),TODAY()-$F251,0)

Sheet Measurement Log
A1: Room | B1: Measurement type | C1: Width | D1: Height | E1: Depth | F1: Length | G1: Ceiling height | H1: Window size | I1: Door size | J1: Wall length | K1: Notes

Sheet Contractor Installer Tracker
A1: Contractor/vendor name | B1: Trade | C1: Contact | D1: Scope | E1: Quote amount | F1: Start date | G1: End date | H1: Payment status | I1: Insurance received | J1: Contract signed | K1: Notes

Sheet Invoice Payment Tracker
A1: Invoice number | B1: Invoice date | C1: Client | D1: Description | E1: Amount | F1: Due date | G1: Paid date | H1: Payment status | I1: Payment method | J1: Notes | K1: Balance due
K2: =IF($A2="","",IF($H2="Paid",0,$E2))
K3: =IF($A3="","",IF($H3="Paid",0,$E3))
K4: =IF($A4="","",IF($H4="Paid",0,$E4))
K5: =IF($A5="","",IF($H5="Paid",0,$E5))
K6: =IF($A6="","",IF($H6="Paid",0,$E6))
K7: =IF($A7="","",IF($H7="Paid",0,$E7))
K8: =IF($A8="","",IF($H8="Paid",0,$E8))
K9: =IF($A9="","",IF($H9="Paid",0,$E9))
K10: =IF($A10="","",IF($H10="Paid",0,$E10))
K11: =IF($A11="","",IF($H11="Paid",0,$E11))
K12: =IF($A12="","",IF($H12="Paid",0,$E12))
K13: =IF($A13="","",IF($H13="Paid",0,$E13))
... K251: =IF($A251="","",IF($H251="Paid",0,$E251))

Sheet Project Meeting Notes
A1: Date | B1: Meeting type | C1: Attendees | D1: Discussion points | E1: Decisions made | F1: Action items | G1: Follow-up date | H1: Notes

Sheet Client FFE Report
A1: Room | B1: Item name | C1: Description | D1: Quantity | E1: Vendor | F1: Product link | G1: Final cost | H1: Approval status | I1: Image link | J1: Client notes
A2: ='Master FF&E Schedule'!B2 | B2: ='Master FF&E Schedule'!D2 | C2: ='Master FF&E Schedule'!E2 | D2: ='Master FF&E Schedule'!F2 | E2: ='Master FF&E Schedule'!K2 | F2: ='Master FF&E Schedule'!M2 | G2: ='Master FF&E Schedule'!T2 | H2: ='Master FF&E Schedule'!W2 | I2: ='Master FF&E Schedule'!AA2
A3: ='Master FF&E Schedule'!B3 | B3: ='Master FF&E Schedule'!D3 | C3: ='Master FF&E Schedule'!E3 | D3: ='Master FF&E Schedule'!F3 | E3: ='Master FF&E Schedule'!K3 | F3: ='Master FF&E Schedule'!M3 | G3: ='Master FF&E Schedule'!T3 | H3: ='Master FF&E Schedule'!W3 | I3: ='Master FF&E Schedule'!AA3
A4: ='Master FF&E Schedule'!B4 | B4: ='Master FF&E Schedule'!D4 | C4: ='Master FF&E Schedule'!E4 | D4: ='Master FF&E Schedule'!F4 | E4: ='Master FF&E Schedule'!K4 | F4: ='Master FF&E Schedule'!M4 | G4: ='Master FF&E Schedule'!T4 | H4: ='Master FF&E Schedule'!W4 | I4: ='Master FF&E Schedule'!AA4
A5: ='Master FF&E Schedule'!B5 | B5: ='Master FF&E Schedule'!D5 | C5: ='Master FF&E Schedule'!E5 | D5: ='Master FF&E Schedule'!F5 | E5: ='Master FF&E Schedule'!K5 | F5: ='Master FF&E Schedule'!M5 | G5: ='Master FF&E Schedule'!T5 | H5: ='Master FF&E Schedule'!W5 | I5: ='Master FF&E Schedule'!AA5
A6: ='Master FF&E Schedule'!B6 | B6: ='Master FF&E Schedule'!D6 | C6: ='Master FF&E Schedule'!E6 | D6: ='Master FF&E Schedule'!F6 | E6: ='Master FF&E Schedule'!K6 | F6: ='Master FF&E Schedule'!M6 | G6: ='Master FF&E Schedule'!T6 | H6: ='Master FF&E Schedule'!W6 | I6: ='Master FF&E Schedule'!AA6
A7: ='Master FF&E Schedule'!B7 | B7: ='Master FF&E Schedule'!D7 | C7: ='Master FF&E Schedule'!E7 | D7: ='Master FF&E Schedule'!F7 | E7: ='Master FF&E Schedule'!K7 | F7: ='Master FF&E Schedule'!M7 | G7: ='Master FF&E Schedule'!T7 | H7: ='Master FF&E Schedule'!W7 | I7: ='Master FF&E Schedule'!AA7
A8: ='Master FF&E Schedule'!B8 | B8: ='Master FF&E Schedule'!D8 | C8: ='Master FF&E Schedule'!E8 | D8: ='Master FF&E Schedule'!F8 | E8: ='Master FF&E Schedule'!K8 | F8: ='Master FF&E Schedule'!M8 | G8: ='Master FF&E Schedule'!T8 | H8: ='Master FF&E Schedule'!W8 | I8: ='Master FF&E Schedule'!AA8
A9: ='Master FF&E Schedule'!B9 | B9: ='Master FF&E Schedule'!D9 | C9: ='Master FF&E Schedule'!E9 | D9: ='Master FF&E Schedule'!F9 | E9: ='Master FF&E Schedule'!K9 | F9: ='Master FF&E Schedule'!M9 | G9: ='Master FF&E Schedule'!T9 | H9: ='Master FF&E Schedule'!W9 | I9: ='Master FF&E Schedule'!AA9
A10: ='Master FF&E Schedule'!B10 | B10: ='Master FF&E Schedule'!D10 | C10: ='Master FF&E Schedule'!E10 | D10: ='Master FF&E Schedule'!F10 | E10: ='Master FF&E Schedule'!K10 | F10: ='Master FF&E Schedule'!M10 | G10: ='Master FF&E Schedule'!T10 | H10: ='Master FF&E Schedule'!W10 | I10: ='Master FF&E Schedule'!AA10
A11: ='Master FF&E Schedule'!B11 | B11: ='Master FF&E Schedule'!D11 | C11: ='Master FF&E Schedule'!E11 | D11: ='Master FF&E Schedule'!F11 | E11: ='Master FF&E Schedule'!K11 | F11: ='Master FF&E Schedule'!M11 | G11: ='Master FF&E Schedule'!T11 | H11: ='Master FF&E Schedule'!W11 | I11: ='Master FF&E Schedule'!AA11
A12: ='Master FF&E Schedule'!B12 | B12: ='Master FF&E Schedule'!D12 | C12: ='Master FF&E Schedule'!E12 | D12: ='Master FF&E Schedule'!F12 | E12: ='Master FF&E Schedule'!K12 | F12: ='Master FF&E Schedule'!M12 | G12: ='Master FF&E Schedule'!T12 | H12: ='Master FF&E Schedule'!W12 | I12: ='Master FF&E Schedule'!AA12
A13: ='Master FF&E Schedule'!B13 | B13: ='Master FF&E Schedule'!D13 | C13: ='Master FF&E Schedule'!E13 | D13: ='Master FF&E Schedule'!F13 | E13: ='Master FF&E Schedule'!K13 | F13: ='Master FF&E Schedule'!M13 | G13: ='Master FF&E Schedule'!T13 | H13: ='Master FF&E Schedule'!W13 | I13: ='Master FF&E Schedule'!AA13
... A251: ='Master FF&E Schedule'!B251 | B251: ='Master FF&E Schedule'!D251 | C251: ='Master FF&E Schedule'!E251 | D251: ='Master FF&E Schedule'!F251 | E251: ='Master FF&E Schedule'!K251 | F251: ='Master FF&E Schedule'!M251 | G251: ='Master FF&E Schedule'!T251 | H251: ='Master FF&E Schedule'!W251 | I251: ='Master FF&E Schedule'!AA251

Sheet Room Budget Report
A1: Room | B1: Budget allocation | C1: Estimated spend | D1: Actual spend | E1: Remaining budget | F1: Budget used % | G1: Status
A2: ='Room List'!A2 | B2: ='Room List'!F2 | C2: ='Room List'!G2 | D2: ='Room List'!H2 | E2: ='Room List'!I2 | F2: =IFERROR(D2/B2,0) | G2: =IF(E2>=0,"On budget","Over budget")
A3: ='Room List'!A3 | B3: ='Room List'!F3 | C3: ='Room List'!G3 | D3: ='Room List'!H3 | E3: ='Room List'!I3 | F3: =IFERROR(D3/B3,0) | G3: =IF(E3>=0,"On budget","Over budget")
A4: ='Room List'!A4 | B4: ='Room List'!F4 | C4: ='Room List'!G4 | D4: ='Room List'!H4 | E4: ='Room List'!I4 | F4: =IFERROR(D4/B4,0) | G4: =IF(E4>=0,"On budget","Over budget")
A5: ='Room List'!A5 | B5: ='Room List'!F5 | C5: ='Room List'!G5 | D5: ='Room List'!H5 | E5: ='Room List'!I5 | F5: =IFERROR(D5/B5,0) | G5: =IF(E5>=0,"On budget","Over budget")
A6: ='Room List'!A6 | B6: ='Room List'!F6 | C6: ='Room List'!G6 | D6: ='Room List'!H6 | E6: ='Room List'!I6 | F6: =IFERROR(D6/B6,0) | G6: =IF(E6>=0,"On budget","Over budget")
A7: ='Room List'!A7 | B7: ='Room List'!F7 | C7: ='Room List'!G7 | D7: ='Room List'!H7 | E7: ='Room List'!I7 | F7: =IFERROR(D7/B7,0) | G7: =IF(E7>=0,"On budget","Over budget")
A8: ='Room List'!A8 | B8: ='Room List'!F8 | C8: ='Room List'!G8 | D8: ='Room List'!H8 | E8: ='Room List'!I8 | F8: =IFERROR(D8/B8,0) | G8: =IF(E8>=0,"On budget","Over budget")
A9: ='Room List'!A9 | B9: ='Room List'!F9 | C9: ='Room List'!G9 | D9: ='Room List'!H9 | E9: ='Room List'!I9 | F9: =IFERROR(D9/B9,0) | G9: =IF(E9>=0,"On budget","Over budget")
A10: ='Room List'!A10 | B10: ='Room List'!F10 | C10: ='Room List'!G10 | D10: ='Room List'!H10 | E10: ='Room List'!I10 | F10: =IFERROR(D10/B10,0) | G10: =IF(E10>=0,"On budget","Over budget")
A11: ='Room List'!A11 | B11: ='Room List'!F11 | C11: ='Room List'!G11 | D11: ='Room List'!H11 | E11: ='Room List'!I11 | F11: =IFERROR(D11/B11,0) | G11: =IF(E11>=0,"On budget","Over budget")
A12: ='Room List'!A12 | B12: ='Room List'!F12 | C12: ='Room List'!G12 | D12: ='Room List'!H12 | E12: ='Room List'!I12 | F12: =IFERROR(D12/B12,0) | G12: =IF(E12>=0,"On budget","Over budget")
A13: ='Room List'!A13 | B13: ='Room List'!F13 | C13: ='Room List'!G13 | D13: ='Room List'!H13 | E13: ='Room List'!I13 | F13: =IFERROR(D13/B13,0) | G13: =IF(E13>=0,"On budget","Over budget")
... A251: ='Room List'!A251 | B251: ='Room List'!F251 | C251: ='Room List'!G251 | D251: ='Room List'!H251 | E251: ='Room List'!I251 | F251: =IFERROR(D251/B251,0) | G251: =IF(E251>=0,"On budget","Over budget")

Sheet Vendor Order Report
A1: Vendor | B1: PO number | C1: Room | D1: Item | E1: Quantity | F1: Order status | G1: Expected delivery date | H1: Amount | I1: Paid status | J1: Tracking number
A2: ='Purchase Order Tracker'!B2 | B2: ='Purchase Order Tracker'!A2 | C2: ='Purchase Order Tracker'!C2 | D2: ='Purchase Order Tracker'!D2 | E2: ='Purchase Order Tracker'!E2 | F2: ='Purchase Order Tracker'!J2 | G2: ='Purchase Order Tracker'!H2 | H2: ='Purchase Order Tracker'!N2 | I2: ='Purchase Order Tracker'!O2 | J2: ='Purchase Order Tracker'!K2
A3: ='Purchase Order Tracker'!B3 | B3: ='Purchase Order Tracker'!A3 | C3: ='Purchase Order Tracker'!C3 | D3: ='Purchase Order Tracker'!D3 | E3: ='Purchase Order Tracker'!E3 | F3: ='Purchase Order Tracker'!J3 | G3: ='Purchase Order Tracker'!H3 | H3: ='Purchase Order Tracker'!N3 | I3: ='Purchase Order Tracker'!O3 | J3: ='Purchase Order Tracker'!K3
A4: ='Purchase Order Tracker'!B4 | B4: ='Purchase Order Tracker'!A4 | C4: ='Purchase Order Tracker'!C4 | D4: ='Purchase Order Tracker'!D4 | E4: ='Purchase Order Tracker'!E4 | F4: ='Purchase Order Tracker'!J4 | G4: ='Purchase Order Tracker'!H4 | H4: ='Purchase Order Tracker'!N4 | I4: ='Purchase Order Tracker'!O4 | J4: ='Purchase Order Tracker'!K4
A5: ='Purchase Order Tracker'!B5 | B5: ='Purchase Order Tracker'!A5 | C5: ='Purchase Order Tracker'!C5 | D5: ='Purchase Order Tracker'!D5 | E5: ='Purchase Order Tracker'!E5 | F5: ='Purchase Order Tracker'!J5 | G5: ='Purchase Order Tracker'!H5 | H5: ='Purchase Order Tracker'!N5 | I5: ='Purchase Order Tracker'!O5 | J5: ='Purchase Order Tracker'!K5
A6: ='Purchase Order Tracker'!B6 | B6: ='Purchase Order Tracker'!A6 | C6: ='Purchase Order Tracker'!C6 | D6: ='Purchase Order Tracker'!D6 | E6: ='Purchase Order Tracker'!E6 | F6: ='Purchase Order Tracker'!J6 | G6: ='Purchase Order Tracker'!H6 | H6: ='Purchase Order Tracker'!N6 | I6: ='Purchase Order Tracker'!O6 | J6: ='Purchase Order Tracker'!K6
A7: ='Purchase Order Tracker'!B7 | B7: ='Purchase Order Tracker'!A7 | C7: ='Purchase Order Tracker'!C7 | D7: ='Purchase Order Tracker'!D7 | E7: ='Purchase Order Tracker'!E7 | F7: ='Purchase Order Tracker'!J7 | G7: ='Purchase Order Tracker'!H7 | H7: ='Purchase Order Tracker'!N7 | I7: ='Purchase Order Tracker'!O7 | J7: ='Purchase Order Tracker'!K7
A8: ='Purchase Order Tracker'!B8 | B8: ='Purchase Order Tracker'!A8 | C8: ='Purchase Order Tracker'!C8 | D8: ='Purchase Order Tracker'!D8 | E8: ='Purchase Order Tracker'!E8 | F8: ='Purchase Order Tracker'!J8 | G8: ='Purchase Order Tracker'!H8 | H8: ='Purchase Order Tracker'!N8 | I8: ='Purchase Order Tracker'!O8 | J8: ='Purchase Order Tracker'!K8
A9: ='Purchase Order Tracker'!B9 | B9: ='Purchase Order Tracker'!A9 | C9: ='Purchase Order Tracker'!C9 | D9: ='Purchase Order Tracker'!D9 | E9: ='Purchase Order Tracker'!E9 | F9: ='Purchase Order Tracker'!J9 | G9: ='Purchase Order Tracker'!H9 | H9: ='Purchase Order Tracker'!N9 | I9: ='Purchase Order Tracker'!O9 | J9: ='Purchase Order Tracker'!K9
A10: ='Purchase Order Tracker'!B10 | B10: ='Purchase Order Tracker'!A10 | C10: ='Purchase Order Tracker'!C10 | D10: ='Purchase Order Tracker'!D10 | E10: ='Purchase Order Tracker'!E10 | F10: ='Purchase Order Tracker'!J10 | G10: ='Purchase Order Tracker'!H10 | H10: ='Purchase Order Tracker'!N10 | I10: ='Purchase Order Tracker'!O10 | J10: ='Purchase Order Tracker'!K10
A11: ='Purchase Order Tracker'!B11 | B11: ='Purchase Order Tracker'!A11 | C11: ='Purchase Order Tracker'!C11 | D11: ='Purchase Order Tracker'!D11 | E11: ='Purchase Order Tracker'!E11 | F11: ='Purchase Order Tracker'!J11 | G11: ='Purchase Order Tracker'!H11 | H11: ='Purchase Order Tracker'!N11 | I11: ='Purchase Order Tracker'!O11 | J11: ='Purchase Order Tracker'!K11
A12: ='Purchase Order Tracker'!B12 | B12: ='Purchase Order Tracker'!A12 | C12: ='Purchase Order Tracker'!C12 | D12: ='Purchase Order Tracker'!D12 | E12: ='Purchase Order Tracker'!E12 | F12: ='Purchase Order Tracker'!J12 | G12: ='Purchase Order Tracker'!H12 | H12: ='Purchase Order Tracker'!N12 | I12: ='Purchase Order Tracker'!O12 | J12: ='Purchase Order Tracker'!K12
A13: ='Purchase Order Tracker'!B13 | B13: ='Purchase Order Tracker'!A13 | C13: ='Purchase Order Tracker'!C13 | D13: ='Purchase Order Tracker'!D13 | E13: ='Purchase Order Tracker'!E13 | F13: ='Purchase Order Tracker'!J13 | G13: ='Purchase Order Tracker'!H13 | H13: ='Purchase Order Tracker'!N13 | I13: ='Purchase Order Tracker'!O13 | J13: ='Purchase Order Tracker'!K13
... A251: ='Purchase Order Tracker'!B251 | B251: ='Purchase Order Tracker'!A251 | C251: ='Purchase Order Tracker'!C251 | D251: ='Purchase Order Tracker'!D251 | E251: ='Purchase Order Tracker'!E251 | F251: ='Purchase Order Tracker'!J251 | G251: ='Purchase Order Tracker'!H251 | H251: ='Purchase Order Tracker'!N251 | I251: ='Purchase Order Tracker'!O251 | J251: ='Purchase Order Tracker'!K251

Sheet Installation Checklist
A1: Room | B1: Item | C1: Vendor | D1: Delivery status | E1: Install date | F1: Installer | G1: Installation status | H1: Damage check | I1: Punch list notes | J1: Complete?
A2: ='Delivery & Installation'!B2 | B2: ='Delivery & Installation'!A2 | C2: ='Delivery & Installation'!C2 | D2: ='Delivery & Installation'!G2 | E2: ='Delivery & Installation'!L2 | F2: ='Delivery & Installation'!M2 | G2: ='Delivery & Installation'!N2 | H2: ='Delivery & Installation'!I2 | I2: ='Delivery & Installation'!O2 | J2: =IF(G2="Installed","Yes","No")
A3: ='Delivery & Installation'!B3 | B3: ='Delivery & Installation'!A3 | C3: ='Delivery & Installation'!C3 | D3: ='Delivery & Installation'!G3 | E3: ='Delivery & Installation'!L3 | F3: ='Delivery & Installation'!M3 | G3: ='Delivery & Installation'!N3 | H3: ='Delivery & Installation'!I3 | I3: ='Delivery & Installation'!O3 | J3: =IF(G3="Installed","Yes","No")
A4: ='Delivery & Installation'!B4 | B4: ='Delivery & Installation'!A4 | C4: ='Delivery & Installation'!C4 | D4: ='Delivery & Installation'!G4 | E4: ='Delivery & Installation'!L4 | F4: ='Delivery & Installation'!M4 | G4: ='Delivery & Installation'!N4 | H4: ='Delivery & Installation'!I4 | I4: ='Delivery & Installation'!O4 | J4: =IF(G4="Installed","Yes","No")
A5: ='Delivery & Installation'!B5 | B5: ='Delivery & Installation'!A5 | C5: ='Delivery & Installation'!C5 | D5: ='Delivery & Installation'!G5 | E5: ='Delivery & Installation'!L5 | F5: ='Delivery & Installation'!M5 | G5: ='Delivery & Installation'!N5 | H5: ='Delivery & Installation'!I5 | I5: ='Delivery & Installation'!O5 | J5: =IF(G5="Installed","Yes","No")
A6: ='Delivery & Installation'!B6 | B6: ='Delivery & Installation'!A6 | C6: ='Delivery & Installation'!C6 | D6: ='Delivery & Installation'!G6 | E6: ='Delivery & Installation'!L6 | F6: ='Delivery & Installation'!M6 | G6: ='Delivery & Installation'!N6 | H6: ='Delivery & Installation'!I6 | I6: ='Delivery & Installation'!O6 | J6: =IF(G6="Installed","Yes","No")
A7: ='Delivery & Installation'!B7 | B7: ='Delivery & Installation'!A7 | C7: ='Delivery & Installation'!C7 | D7: ='Delivery & Installation'!G7 | E7: ='Delivery & Installation'!L7 | F7: ='Delivery & Installation'!M7 | G7: ='Delivery & Installation'!N7 | H7: ='Delivery & Installation'!I7 | I7: ='Delivery & Installation'!O7 | J7: =IF(G7="Installed","Yes","No")
A8: ='Delivery & Installation'!B8 | B8: ='Delivery & Installation'!A8 | C8: ='Delivery & Installation'!C8 | D8: ='Delivery & Installation'!G8 | E8: ='Delivery & Installation'!L8 | F8: ='Delivery & Installation'!M8 | G8: ='Delivery & Installation'!N8 | H8: ='Delivery & Installation'!I8 | I8: ='Delivery & Installation'!O8 | J8: =IF(G8="Installed","Yes","No")
A9: ='Delivery & Installation'!B9 | B9: ='Delivery & Installation'!A9 | C9: ='Delivery & Installation'!C9 | D9: ='Delivery & Installation'!G9 | E9: ='Delivery & Installation'!L9 | F9: ='Delivery & Installation'!M9 | G9: ='Delivery & Installation'!N9 | H9: ='Delivery & Installation'!I9 | I9: ='Delivery & Installation'!O9 | J9: =IF(G9="Installed","Yes","No")
A10: ='Delivery & Installation'!B10 | B10: ='Delivery & Installation'!A10 | C10: ='Delivery & Installation'!C10 | D10: ='Delivery & Installation'!G10 | E10: ='Delivery & Installation'!L10 | F10: ='Delivery & Installation'!M10 | G10: ='Delivery & Installation'!N10 | H10: ='Delivery & Installation'!I10 | I10: ='Delivery & Installation'!O10 | J10: =IF(G10="Installed","Yes","No")
A11: ='Delivery & Installation'!B11 | B11: ='Delivery & Installation'!A11 | C11: ='Delivery & Installation'!C11 | D11: ='Delivery & Installation'!G11 | E11: ='Delivery & Installation'!L11 | F11: ='Delivery & Installation'!M11 | G11: ='Delivery & Installation'!N11 | H11: ='Delivery & Installation'!I11 | I11: ='Delivery & Installation'!O11 | J11: =IF(G11="Installed","Yes","No")
A12: ='Delivery & Installation'!B12 | B12: ='Delivery & Installation'!A12 | C12: ='Delivery & Installation'!C12 | D12: ='Delivery & Installation'!G12 | E12: ='Delivery & Installation'!L12 | F12: ='Delivery & Installation'!M12 | G12: ='Delivery & Installation'!N12 | H12: ='Delivery & Installation'!I12 | I12: ='Delivery & Installation'!O12 | J12: =IF(G12="Installed","Yes","No")
A13: ='Delivery & Installation'!B13 | B13: ='Delivery & Installation'!A13 | C13: ='Delivery & Installation'!C13 | D13: ='Delivery & Installation'!G13 | E13: ='Delivery & Installation'!L13 | F13: ='Delivery & Installation'!M13 | G13: ='Delivery & Installation'!N13 | H13: ='Delivery & Installation'!I13 | I13: ='Delivery & Installation'!O13 | J13: =IF(G13="Installed","Yes","No")
... A251: ='Delivery & Installation'!B251 | B251: ='Delivery & Installation'!A251 | C251: ='Delivery & Installation'!C251 | D251: ='Delivery & Installation'!G251 | E251: ='Delivery & Installation'!L251 | F251: ='Delivery & Installation'!M251 | G251: ='Delivery & Installation'!N251 | H251: ='Delivery & Installation'!I251 | I251: ='Delivery & Installation'!O251 | J251: =IF(G251="Installed","Yes","No")

Sheet Final Punch List
A1: Room | B1: Issue/item | C1: Responsible party | D1: Priority | E1: Due date | F1: Status | G1: Resolution notes | H1: Completed date

Sheet Lists
A1: projectTypes | B1: yesNo | C1: projectStatuses | D1: billingMethods | E1: designStatuses | F1: priorities | G1: roomTypes | H1: ffeCategories | I1: itemStatuses | J1: orderStatuses | K1: approvalStatuses | L1: deliveryStatuses | M1: installStatuses | N1: fixtureTypes | O1: finishTypes | P1: surfaces | Q1: vendorTypes | R1: budgetCategories | S1: damageChecks | T1: approvalTypes | U1: phases | V1: taskStatuses | W1: measurementTypes | X1: trades | Y1: paymentStatuses | Z1: meetingTypes | AA1: preferredOptions
A2: Residential | B2: Yes | C2: Not started | D2: Flat fee | E2: Not started | F2: Low | G2: Living room | H2: Sofa | I2: Sourcing | J2: Not ordered | K2: Not sent | L2: Not ordered | M2: Not scheduled | N2: Lighting | O2: Paint | P2: Wall | Q2: Furniture | R2: Furniture | S2: Not checked | T2: Furniture | U2: Consultation | V2: Not started | W2: Room | X2: General contractor | Y2: Draft | Z2: Client consultation | AA2: Option 1
A3: Commercial | B3: No | C3: In progress | D3: Hourly | E3: Concept | F3: Medium | G3: Bedroom | H3: Chair | I3: Option selected | J3: Ordered | K3: Sent | L3: Ordered | M3: Scheduled | N3: Faucet | O3: Wallpaper | P3: Ceiling | Q3: Lighting | R3: Lighting | S3: Good condition | T3: Finish | U3: Measurements | V3: In progress | W3: Wall | X3: Painter | Y3: Sent | Z3: Vendor meeting | AA3: Option 2
A4: Office | C4: On hold | D4: Percentage | E4: Sourcing | F4: High | G4: Kitchen | H4: Table | I4: Client review | J4: Confirmed | K4: Client review | L4: Shipped | M4: Installed | N4: Sink | O4: Flooring | P4: Floor | Q4: Fabric | R4: Rugs | S4: Damaged | T4: Layout | U4: Concept design | V4: Waiting on client | W4: Window | X4: Electrician | Y4: Paid | Z4: Site visit | AA4: Option 3
A5: Retail | C5: Complete | D5: Hybrid | E5: Client review | F5: Urgent | G5: Bathroom | H5: Bed | I5: Approved | J5: In production | K5: Approved | L5: Delivered | M5: Punch list | N5: Shower fixture | O5: Tile | P5: Cabinet | Q5: Flooring | R5: Decor | S5: Missing item | T5: Color palette | U5: Sourcing | V5: Waiting on vendor | W5: Door | X5: Plumber | Y5: Partially paid | Z5: Installation meeting
A6: Hospitality | C6: Delayed | E6: Approved | G6: Dining room | H6: Rug | I6: Ordered | J6: Shipped | K6: Revisions requested | L6: Delayed | M6: Delayed | N6: Tub | O6: Countertop | P6: Countertop | Q6: Tile | R6: Artwork | S6: Wrong item | T6: Budget | U6: Client approval | V6: Complete | W6: Cabinet | X6: Flooring installer | Y6: Overdue | Z6: Contractor meeting
A7: Staging | C7: Cancelled | E7: Ordered | G7: Entryway | H7: Lighting | I7: Shipped | J7: Delivered | K7: Rejected | L7: Cancelled | M7: Cancelled | N7: Toilet | O7: Backsplash | P7: Shower wall | Q7: Paint | R7: Window treatments | T7: Purchase | U7: Purchasing | V7: Delayed | W7: Furniture space | X7: Tile installer | Y7: Cancelled | Z7: Final walkthrough
E8: Installed | G8: Office | H8: Artwork | I8: Delivered | J8: Delayed | K8: On hold | L8: Returned | N8: Cabinet hardware | O8: Cabinet finish | P8: Backsplash | Q8: Wallpaper | R8: Flooring | T8: Vendor | U8: Construction | W8: Rug area | X8: Wallpaper installer | Y8: Unpaid
E9: Complete | G9: Nursery | H9: Mirror | I9: Installed | J9: Cancelled | L9: Backordered | N9: Door hardware | O9: Fabric | P9: Upholstery | Q9: Decor | R9: Paint/wallcovering | T9: Design concept | U9: Delivery | W9: Lighting location | X9: Carpenter
E10: On hold | G10: Outdoor | H10: Window treatment | I10: Cancelled | J10: Returned | N10: Appliance | O10: Trim | P10: Drapery | Q10: Hardware | R10: Contractor labor | U10: Installation | X10: Window treatment installer
G11: Commercial space | H11: Hardware | I11: Backordered | N11: Electrical | O11: Stone | Q11: Contractor | R11: Installation | U11: Styling | X11: Furniture installer
G12: Other | H12: Plumbing fixture | N12: Other | O12: Wood | Q12: Installer | R12: Shipping | U12: Final reveal | X12: Cleaner
H13: Appliance | O13: Metal | Q13: Workroom | R13: Taxes | U13: Punch list | X13: Other
H14: Decor | O14: Other | Q14: Custom furniture | R14: Design fee
H15: Textile | Q15: Other | R15: Contingency
H16: Cabinetry
H17: Flooring
H18: Wallcovering
H19: Other
