Workbook
Name ApprovalStatuses: Lists!$I$2:$I$8
Name ApprovalTrackerStatuses: Lists!$U$2:$U$7
Name ApprovalTypes: Lists!$T$2:$T$9
Name BillingMethods: Lists!$D$2:$D$5
Name BudgetCategories: Lists!$Q$2:$Q$15
Name Categories: Lists!$H$2:$H$19
Name DamageChecks: Lists!$S$2:$S$6
Name DeliveryStatuses: Lists!$K$2:$K$8
Name DesignStatuses: Lists!$G$2:$G$10
Name FinishTypes: Lists!$N$2:$N$14
Name FixtureTypes: Lists!$M$2:$M$12
Name InstallStatuses: Lists!$L$2:$L$8
Name InvoiceStatuses: Lists!$Z$2:$Z$7
Name MeasurementTypes: Lists!$X$2:$X$9
Name MeetingTypes: Lists!$AA$2:$AA$7
Name OrderStatuses: Lists!$J$2:$J$15
Name PaymentStatuses: Lists!$R$2:$R$9
Name Phases: Lists!$V$2:$V$13
Name Priorities: Lists!$F$2:$F$5
Name ProjectBudget: 'Client & Project Profile'!$B$13
Name ProjectStatuses: Lists!$C$2:$C$7
Name ProjectTypes: Lists!$B$2:$B$7
Name RoomNames: 'Room List'!$A$4:$A$253
Name RoomTypes: Lists!$A$2:$A$12
Name Surfaces: Lists!$O$2:$O$11
Name TaskStatuses: Lists!$W$2:$W$7
Name Trades: Lists!$Y$2:$Y$13
Name VendorNames: 'Vendor Database'!$A$4:$A$253
Name VendorTypes: Lists!$P$2:$P$15
Name YesNo: Lists!$E$2:$E$3

Sheet Welcome
A1: INTERIOR DESIGN PROJECT MANAGER
A2: Excel + Google Sheets compatible • Fully editable and unlocked • No macros required
B4: QUICK START GUIDE
B5: Step 1 | C5: Add client/project details | D5: Complete the Client & Project Profile, including total budget and target dates.
B6: Step 2 | C6: Add rooms | D6: List each space in Room List. Room names become your standard reference across schedules.
B7: Step 3 | C7: Add FF&E items | D7: Use Master FF&E for furniture, fixtures and equipment. Add product links, quantities and costs.
B8: Step 4 | C8: Track execution | D8: Update approvals, orders, delivery, installation, budget and tasks as the project progresses.
B9: Step 5 | C9: Review the dashboard | D9: Use Project Dashboard for KPIs, risks and visual project summaries.
B12: HOW TO USE THIS WORKBOOK
B13: Data entry | C13: Enter information in white cells. Blue-tinted cells contain formulas and calculate automatically. Do not paste over formula columns.
B14: Dropdowns | C14: Click a dropdown cell and choose a standard value. Dropdowns improve dashboard accuracy. Room and vendor dropdowns use the Room List and Vendor Database.
B15: Color coding | C15: Green = complete/approved/on budget • Yellow = pending/in progress • Red = overdue/over budget/delayed • Gray = cancelled/on hold.
B16: Filters | C16: Use the arrows in schedule headers to filter by room, vendor, status, approval or date. Clear filters to show all records.
B17: Compatibility | C17: Designed for Microsoft Excel (.xlsx) and Google Sheets. To use in Sheets: File → Import → Upload. Some chart styling may vary slightly.
B18: Editable version | C18: This workbook is fully editable and unlocked. Duplicate the original before customizing formulas, colors or tab names.
B19: Support | C19: Add your business support email, website or product documentation link here before distributing this template.
B22: WHAT EACH TAB IS FOR
B23: Dashboard — project KPIs and charts
B24: Profile / Room List — project setup and space budgets
B25: Master FF&E — central product and cost schedule
B26: Furniture / Fixtures / Finishes — focused specifications
B27: Sourcing / Vendors — compare products and manage suppliers
B28: Budget / Orders / Delivery — purchasing controls
B29: Approvals / Timeline / Tasks — project workflow
B30: Measurements / Contractors / Invoices / Notes — field and admin records
B31: Reports — printable client, budget, vendor and installation views

Sheet Project Dashboard
A1: PROJECT DASHBOARD
A2: Live overview • Complete the Profile, Room List, FF&E, Orders, Approvals and Tasks tabs to populate metrics.
A4: Total Project Budget | E4: Total Estimated Cost | I4: Total Actual Cost | M4: Remaining Budget
A5: =ProjectBudget -> 0 | E5: =SUM('Master FF&E'!$P$4:$P$253) -> 0 | I5: =SUM('Master FF&E'!$T$4:$T$253) -> 0 | M5: =ProjectBudget-SUM('Master FF&E'!$T$4:$T$253) -> 0
A7: Budget Used % | E7: Number of Rooms | I7: Total FF&E Items | M7: Items Approved
A8: =IFERROR(SUM('Master FF&E'!$T$4:$T$253)/ProjectBudget,0) -> 0 | E8: =COUNTIF('Room List'!$A$4:$A$253,"<>") -> 0 | I8: =COUNTIF('Master FF&E'!$A$4:$A$253,"<>") -> 0 | M8: =COUNTIF('Master FF&E'!$W$4:$W$253,"Approved") -> 0
A10: Items Ordered | E10: Items Delivered | I10: Items Installed | M10: Overdue Tasks
A11: =COUNTIF('Master FF&E'!$V$4:$V$253,"Ordered")+COUNTIF('Master FF&E'!$V$4:$V$253,"Confirmed") -> 0 | E11: =COUNTIF('Master FF&E'!$X$4:$X$253,"Delivered") -> 0 | I11: =COUNTIF('Master FF&E'!$Y$4:$Y$253,"Installed")+COUNTIF('Master FF&E'!$Y$4:$Y$253,"Complete") -> 0 | M11: =COUNTIFS('Task List'!$F$4:$F$253,"<"&TODAY(),'Task List'!$F$4:$F$253,"<>",'Task List'!$G$4:$G$253,"<>Complete") -> 0
A13: Pending Client Approvals | E13: Open Vendor Orders | I13: Items Not Ordered | M13: Delivered, Not Installed
A14: =COUNTIF('Client Approvals'!$F$4:$F$253,"Sent")+COUNTIF('Client Approvals'!$F$4:$F$253,"Revisions requested") -> 0 | E14: =COUNTIFS('Order Tracker'!$A$4:$A$253,"<>",'Order Tracker'!$J$4:$J$253,"<>Delivered",'Order Tracker'!$J$4:$J$253,"<>Cancelled",'Order Tracker'!$J$4:$J$253,"<>Returned") -> 0 | I14: =COUNTIFS('Master FF&E'!$A$4:$A$253,"<>",'Master FF&E'!$V$4:$V$253,"<>Ordered",'Master FF&E'!$V$4:$V$253,"<>Confirmed",'Master FF&E'!$V$4:$V$253,"<>In production",'Master FF&E'!$V$4:$V$253,"<>Shipped",'Master FF&E'!$V$4:$V$253,"<>Delivered",'Master FF&E'!$V$4:$V$253,"<>Cancelled") -> 0 | M14: =COUNTIFS('Master FF&E'!$X$4:$X$253,"Delivered",'Master FF&E'!$Y$4:$Y$253,"<>Installed",'Master FF&E'!$Y$4:$Y$253,"<>Complete") -> 0
Q19: Room | R19: Budget | S19: Actual | U19: Budget Category | V19: Budgeted | W19: Actual | Y19: Item Status | Z19: Count | AB19: Delivery Status | AC19: Count | AE19: Category | AF19: Spend
Q20: ='Room List'!A4 -> 0 | R20: ='Room List'!F4 -> 0 | S20: ='Room List'!H4 -> 0 | U20: Furniture | V20: =SUMIF('Budget Tracker'!$A$4:$A$253,U20,'Budget Tracker'!$B$4:$B$253) -> 0 | W20: =SUMIF('Budget Tracker'!$A$4:$A$253,U20,'Budget Tracker'!$D$4:$D$253) -> 0 | Y20: Sourcing | Z20: =COUNTIF('Master FF&E'!$V$4:$V$253,Y20) -> 0 | AB20: Not scheduled | AC20: =COUNTIF('Master FF&E'!$X$4:$X$253,AB20) -> 0 | AE20: Sofa | AF20: =SUMIF('Master FF&E'!$C$4:$C$253,AE20,'Master FF&E'!$T$4:$T$253) -> 0
Q21: ='Room List'!A5 -> 0 | R21: ='Room List'!F5 -> 0 | S21: ='Room List'!H5 -> 0 | U21: Lighting | V21: =SUMIF('Budget Tracker'!$A$4:$A$253,U21,'Budget Tracker'!$B$4:$B$253) -> 0 | W21: =SUMIF('Budget Tracker'!$A$4:$A$253,U21,'Budget Tracker'!$D$4:$D$253) -> 0 | Y21: Option selected | Z21: =COUNTIF('Master FF&E'!$V$4:$V$253,Y21) -> 0 | AB21: Scheduled | AC21: =COUNTIF('Master FF&E'!$X$4:$X$253,AB21) -> 0 | AE21: Chair | AF21: =SUMIF('Master FF&E'!$C$4:$C$253,AE21,'Master FF&E'!$T$4:$T$253) -> 0
Q22: ='Room List'!A6 -> 0 | R22: ='Room List'!F6 -> 0 | S22: ='Room List'!H6 -> 0 | U22: Rugs | V22: =SUMIF('Budget Tracker'!$A$4:$A$253,U22,'Budget Tracker'!$B$4:$B$253) -> 0 | W22: =SUMIF('Budget Tracker'!$A$4:$A$253,U22,'Budget Tracker'!$D$4:$D$253) -> 0 | Y22: Client review | Z22: =COUNTIF('Master FF&E'!$V$4:$V$253,Y22) -> 0 | AB22: In transit | AC22: =COUNTIF('Master FF&E'!$X$4:$X$253,AB22) -> 0 | AE22: Table | AF22: =SUMIF('Master FF&E'!$C$4:$C$253,AE22,'Master FF&E'!$T$4:$T$253) -> 0
Q23: ='Room List'!A7 -> 0 | R23: ='Room List'!F7 -> 0 | S23: ='Room List'!H7 -> 0 | U23: Decor | V23: =SUMIF('Budget Tracker'!$A$4:$A$253,U23,'Budget Tracker'!$B$4:$B$253) -> 0 | W23: =SUMIF('Budget Tracker'!$A$4:$A$253,U23,'Budget Tracker'!$D$4:$D$253) -> 0 | Y23: Approved | Z23: =COUNTIF('Master FF&E'!$V$4:$V$253,Y23) -> 0 | AB23: Delivered | AC23: =COUNTIF('Master FF&E'!$X$4:$X$253,AB23) -> 0 | AE23: Bed | AF23: =SUMIF('Master FF&E'!$C$4:$C$253,AE23,'Master FF&E'!$T$4:$T$253) -> 0
Q24: ='Room List'!A8 -> 0 | R24: ='Room List'!F8 -> 0 | S24: ='Room List'!H8 -> 0 | U24: Artwork | V24: =SUMIF('Budget Tracker'!$A$4:$A$253,U24,'Budget Tracker'!$B$4:$B$253) -> 0 | W24: =SUMIF('Budget Tracker'!$A$4:$A$253,U24,'Budget Tracker'!$D$4:$D$253) -> 0 | Y24: Ordered | Z24: =COUNTIF('Master FF&E'!$V$4:$V$253,Y24) -> 0 | AB24: Delayed | AC24: =COUNTIF('Master FF&E'!$X$4:$X$253,AB24) -> 0 | AE24: Rug | AF24: =SUMIF('Master FF&E'!$C$4:$C$253,AE24,'Master FF&E'!$T$4:$T$253) -> 0
Q25: ='Room List'!A9 -> 0 | R25: ='Room List'!F9 -> 0 | S25: ='Room List'!H9 -> 0 | U25: Window treatments | V25: =SUMIF('Budget Tracker'!$A$4:$A$253,U25,'Budget Tracker'!$B$4:$B$253) -> 0 | W25: =SUMIF('Budget Tracker'!$A$4:$A$253,U25,'Budget Tracker'!$D$4:$D$253) -> 0 | Y25: Shipped | Z25: =COUNTIF('Master FF&E'!$V$4:$V$253,Y25) -> 0 | AB25: Cancelled | AC25: =COUNTIF('Master FF&E'!$X$4:$X$253,AB25) -> 0 | AE25: Lighting | AF25: =SUMIF('Master FF&E'!$C$4:$C$253,AE25,'Master FF&E'!$T$4:$T$253) -> 0
Q26: ='Room List'!A10 -> 0 | R26: ='Room List'!F10 -> 0 | S26: ='Room List'!H10 -> 0 | U26: Flooring | V26: =SUMIF('Budget Tracker'!$A$4:$A$253,U26,'Budget Tracker'!$B$4:$B$253) -> 0 | W26: =SUMIF('Budget Tracker'!$A$4:$A$253,U26,'Budget Tracker'!$D$4:$D$253) -> 0 | Y26: Delivered | Z26: =COUNTIF('Master FF&E'!$V$4:$V$253,Y26) -> 0 | AB26: Returned | AC26: =COUNTIF('Master FF&E'!$X$4:$X$253,AB26) -> 0 | AE26: Artwork | AF26: =SUMIF('Master FF&E'!$C$4:$C$253,AE26,'Master FF&E'!$T$4:$T$253) -> 0
Q27: ='Room List'!A11 -> 0 | R27: ='Room List'!F11 -> 0 | S27: ='Room List'!H11 -> 0 | U27: Paint/wallcovering | V27: =SUMIF('Budget Tracker'!$A$4:$A$253,U27,'Budget Tracker'!$B$4:$B$253) -> 0 | W27: =SUMIF('Budget Tracker'!$A$4:$A$253,U27,'Budget Tracker'!$D$4:$D$253) -> 0 | Y27: Installed | Z27: =COUNTIF('Master FF&E'!$V$4:$V$253,Y27) -> 0 | AE27: Mirror | AF27: =SUMIF('Master FF&E'!$C$4:$C$253,AE27,'Master FF&E'!$T$4:$T$253) -> 0
Q28: ='Room List'!A12 -> 0 | R28: ='Room List'!F12 -> 0 | S28: ='Room List'!H12 -> 0 | U28: Contractor labor | V28: =SUMIF('Budget Tracker'!$A$4:$A$253,U28,'Budget Tracker'!$B$4:$B$253) -> 0 | W28: =SUMIF('Budget Tracker'!$A$4:$A$253,U28,'Budget Tracker'!$D$4:$D$253) -> 0 | Y28: Cancelled | Z28: =COUNTIF('Master FF&E'!$V$4:$V$253,Y28) -> 0 | AE28: Window treatment | AF28: =SUMIF('Master FF&E'!$C$4:$C$253,AE28,'Master FF&E'!$T$4:$T$253) -> 0
Q29: ='Room List'!A13 -> 0 | R29: ='Room List'!F13 -> 0 | S29: ='Room List'!H13 -> 0 | U29: Installation | V29: =SUMIF('Budget Tracker'!$A$4:$A$253,U29,'Budget Tracker'!$B$4:$B$253) -> 0 | W29: =SUMIF('Budget Tracker'!$A$4:$A$253,U29,'Budget Tracker'!$D$4:$D$253) -> 0 | Y29: Backordered | Z29: =COUNTIF('Master FF&E'!$V$4:$V$253,Y29) -> 0 | AE29: Hardware | AF29: =SUMIF('Master FF&E'!$C$4:$C$253,AE29,'Master FF&E'!$T$4:$T$253) -> 0
Q30: ='Room List'!A14 -> 0 | R30: ='Room List'!F14 -> 0 | S30: ='Room List'!H14 -> 0 | U30: Shipping | V30: =SUMIF('Budget Tracker'!$A$4:$A$253,U30,'Budget Tracker'!$B$4:$B$253) -> 0 | W30: =SUMIF('Budget Tracker'!$A$4:$A$253,U30,'Budget Tracker'!$D$4:$D$253) -> 0 | AE30: Plumbing fixture | AF30: =SUMIF('Master FF&E'!$C$4:$C$253,AE30,'Master FF&E'!$T$4:$T$253) -> 0
Q31: ='Room List'!A15 -> 0 | R31: ='Room List'!F15 -> 0 | S31: ='Room List'!H15 -> 0 | U31: Taxes | V31: =SUMIF('Budget Tracker'!$A$4:$A$253,U31,'Budget Tracker'!$B$4:$B$253) -> 0 | W31: =SUMIF('Budget Tracker'!$A$4:$A$253,U31,'Budget Tracker'!$D$4:$D$253) -> 0 | AE31: Appliance | AF31: =SUMIF('Master FF&E'!$C$4:$C$253,AE31,'Master FF&E'!$T$4:$T$253) -> 0
Q32: ='Room List'!A16 -> 0 | R32: ='Room List'!F16 -> 0 | S32: ='Room List'!H16 -> 0 | U32: Design fee | V32: =SUMIF('Budget Tracker'!$A$4:$A$253,U32,'Budget Tracker'!$B$4:$B$253) -> 0 | W32: =SUMIF('Budget Tracker'!$A$4:$A$253,U32,'Budget Tracker'!$D$4:$D$253) -> 0 | AE32: Decor | AF32: =SUMIF('Master FF&E'!$C$4:$C$253,AE32,'Master FF&E'!$T$4:$T$253) -> 0
Q33: ='Room List'!A17 -> 0 | R33: ='Room List'!F17 -> 0 | S33: ='Room List'!H17 -> 0 | U33: Contingency | V33: =SUMIF('Budget Tracker'!$A$4:$A$253,U33,'Budget Tracker'!$B$4:$B$253) -> 0 | W33: =SUMIF('Budget Tracker'!$A$4:$A$253,U33,'Budget Tracker'!$D$4:$D$253) -> 0 | AE33: Textile | AF33: =SUMIF('Master FF&E'!$C$4:$C$253,AE33,'Master FF&E'!$T$4:$T$253) -> 0
Q34: ='Room List'!A18 -> 0 | R34: ='Room List'!F18 -> 0 | S34: ='Room List'!H18 -> 0 | AE34: Cabinetry | AF34: =SUMIF('Master FF&E'!$C$4:$C$253,AE34,'Master FF&E'!$T$4:$T$253) -> 0
AE35: Flooring | AF35: =SUMIF('Master FF&E'!$C$4:$C$253,AE35,'Master FF&E'!$T$4:$T$253) -> 0
AE36: Wallcovering | AF36: =SUMIF('Master FF&E'!$C$4:$C$253,AE36,'Master FF&E'!$T$4:$T$253) -> 0
AE37: Other | AF37: =SUMIF('Master FF&E'!$C$4:$C$253,AE37,'Master FF&E'!$T$4:$T$253) -> 0

Sheet Client & Project Profile
A1: CLIENT & PROJECT PROFILE
A2: Complete this tab first. Dashboard budget and dates reference these values.
A4: Client name | D4: Scope summary
A5: Client email
A6: Phone number
A7: Project name
A8: Project address
A9: Project type
A10: Design style
A11: Start date
A12: Target completion date | D12: Client notes
A13: Total budget
A14: Designer name
A15: Project status
A16: Contract signed
A17: Deposit paid
A18: Design package selected
A19: Billing method

Sheet Room List
A1: Room List
A2: Use filters in the header row. White cells are inputs; blue cells are formulas.
A3: Room Name | B3: Room Type | C3: Floor / Level | D3: Square Footage | E3: Design Status | F3: Budget Allocation | G3: Estimated Spend | H3: Actual Spend | I3: Remaining Budget | J3: Priority Level | K3: Notes
G4: =IF($A4="","",SUMIF('Master FF&E'!$B$4:$B$253,$A4,'Master FF&E'!$P$4:$P$253)) -> 0 | H4: =IF($A4="","",SUMIF('Master FF&E'!$B$4:$B$253,$A4,'Master FF&E'!$T$4:$T$253)) -> 0 | I4: =IF($A4="","",F4-H4) -> 0
G5: =IF($A5="","",SUMIF('Master FF&E'!$B$4:$B$253,$A5,'Master FF&E'!$P$4:$P$253)) -> 0 | H5: =IF($A5="","",SUMIF('Master FF&E'!$B$4:$B$253,$A5,'Master FF&E'!$T$4:$T$253)) -> 0 | I5: =IF($A5="","",F5-H5) -> 0
G6: =IF($A6="","",SUMIF('Master FF&E'!$B$4:$B$253,$A6,'Master FF&E'!$P$4:$P$253)) -> 0 | H6: =IF($A6="","",SUMIF('Master FF&E'!$B$4:$B$253,$A6,'Master FF&E'!$T$4:$T$253)) -> 0 | I6: =IF($A6="","",F6-H6) -> 0
G7: =IF($A7="","",SUMIF('Master FF&E'!$B$4:$B$253,$A7,'Master FF&E'!$P$4:$P$253)) -> 0 | H7: =IF($A7="","",SUMIF('Master FF&E'!$B$4:$B$253,$A7,'Master FF&E'!$T$4:$T$253)) -> 0 | I7: =IF($A7="","",F7-H7) -> 0
G8: =IF($A8="","",SUMIF('Master FF&E'!$B$4:$B$253,$A8,'Master FF&E'!$P$4:$P$253)) -> 0 | H8: =IF($A8="","",SUMIF('Master FF&E'!$B$4:$B$253,$A8,'Master FF&E'!$T$4:$T$253)) -> 0 | I8: =IF($A8="","",F8-H8) -> 0
G9: =IF($A9="","",SUMIF('Master FF&E'!$B$4:$B$253,$A9,'Master FF&E'!$P$4:$P$253)) -> 0 | H9: =IF($A9="","",SUMIF('Master FF&E'!$B$4:$B$253,$A9,'Master FF&E'!$T$4:$T$253)) -> 0 | I9: =IF($A9="","",F9-H9) -> 0
G10: =IF($A10="","",SUMIF('Master FF&E'!$B$4:$B$253,$A10,'Master FF&E'!$P$4:$P$253)) -> 0 | H10: =IF($A10="","",SUMIF('Master FF&E'!$B$4:$B$253,$A10,'Master FF&E'!$T$4:$T$253)) -> 0 | I10: =IF($A10="","",F10-H10) -> 0
G11: =IF($A11="","",SUMIF('Master FF&E'!$B$4:$B$253,$A11,'Master FF&E'!$P$4:$P$253)) -> 0 | H11: =IF($A11="","",SUMIF('Master FF&E'!$B$4:$B$253,$A11,'Master FF&E'!$T$4:$T$253)) -> 0 | I11: =IF($A11="","",F11-H11) -> 0
G12: =IF($A12="","",SUMIF('Master FF&E'!$B$4:$B$253,$A12,'Master FF&E'!$P$4:$P$253)) -> 0 | H12: =IF($A12="","",SUMIF('Master FF&E'!$B$4:$B$253,$A12,'Master FF&E'!$T$4:$T$253)) -> 0 | I12: =IF($A12="","",F12-H12) -> 0
G13: =IF($A13="","",SUMIF('Master FF&E'!$B$4:$B$253,$A13,'Master FF&E'!$P$4:$P$253)) -> 0 | H13: =IF($A13="","",SUMIF('Master FF&E'!$B$4:$B$253,$A13,'Master FF&E'!$T$4:$T$253)) -> 0 | I13: =IF($A13="","",F13-H13) -> 0
G14: =IF($A14="","",SUMIF('Master FF&E'!$B$4:$B$253,$A14,'Master FF&E'!$P$4:$P$253)) -> 0 | H14: =IF($A14="","",SUMIF('Master FF&E'!$B$4:$B$253,$A14,'Master FF&E'!$T$4:$T$253)) -> 0 | I14: =IF($A14="","",F14-H14) -> 0
G15: =IF($A15="","",SUMIF('Master FF&E'!$B$4:$B$253,$A15,'Master FF&E'!$P$4:$P$253)) -> 0 | H15: =IF($A15="","",SUMIF('Master FF&E'!$B$4:$B$253,$A15,'Master FF&E'!$T$4:$T$253)) -> 0 | I15: =IF($A15="","",F15-H15) -> 0
... G253: =IF($A253="","",SUMIF('Master FF&E'!$B$4:$B$253,$A253,'Master FF&E'!$P$4:$P$253)) -> 0 | H253: =IF($A253="","",SUMIF('Master FF&E'!$B$4:$B$253,$A253,'Master FF&E'!$T$4:$T$253)) -> 0 | I253: =IF($A253="","",F253-H253) -> 0

Sheet Master FF&E
A1: Master FF&E
A2: Furniture, Fixtures & Equipment master schedule. Total Cost = Quantity × Unit Cost; Final Cost = Total + Tax + Shipping − Discount.
A3: Item ID | B3: Room | C3: Category | D3: Item Name | E3: Description | F3: Quantity | G3: Dimensions | H3: Material | I3: Finish | J3: Color | K3: Vendor | L3: Brand | M3: Product Link | N3: SKU / Model Number | O3: Unit Cost | P3: Total Cost | Q3: Tax ($) | R3: Shipping ($) | S3: Discount ($) | T3: Final Cost | U3: Lead Time | V3: Order Status | W3: Approval Status | X3: Delivery Status | Y3: Install Status | Z3: Notes | AA3: Image Link
P4: =IF(OR(F4="",O4=""),"",F4*O4) -> 0 | T4: =IF(P4="","",P4+N(Q4)+N(R4)-N(S4)) -> 0
P5: =IF(OR(F5="",O5=""),"",F5*O5) -> 0 | T5: =IF(P5="","",P5+N(Q5)+N(R5)-N(S5)) -> 0
P6: =IF(OR(F6="",O6=""),"",F6*O6) -> 0 | T6: =IF(P6="","",P6+N(Q6)+N(R6)-N(S6)) -> 0
P7: =IF(OR(F7="",O7=""),"",F7*O7) -> 0 | T7: =IF(P7="","",P7+N(Q7)+N(R7)-N(S7)) -> 0
P8: =IF(OR(F8="",O8=""),"",F8*O8) -> 0 | T8: =IF(P8="","",P8+N(Q8)+N(R8)-N(S8)) -> 0
P9: =IF(OR(F9="",O9=""),"",F9*O9) -> 0 | T9: =IF(P9="","",P9+N(Q9)+N(R9)-N(S9)) -> 0
P10: =IF(OR(F10="",O10=""),"",F10*O10) -> 0 | T10: =IF(P10="","",P10+N(Q10)+N(R10)-N(S10)) -> 0
P11: =IF(OR(F11="",O11=""),"",F11*O11) -> 0 | T11: =IF(P11="","",P11+N(Q11)+N(R11)-N(S11)) -> 0
P12: =IF(OR(F12="",O12=""),"",F12*O12) -> 0 | T12: =IF(P12="","",P12+N(Q12)+N(R12)-N(S12)) -> 0
P13: =IF(OR(F13="",O13=""),"",F13*O13) -> 0 | T13: =IF(P13="","",P13+N(Q13)+N(R13)-N(S13)) -> 0
P14: =IF(OR(F14="",O14=""),"",F14*O14) -> 0 | T14: =IF(P14="","",P14+N(Q14)+N(R14)-N(S14)) -> 0
P15: =IF(OR(F15="",O15=""),"",F15*O15) -> 0 | T15: =IF(P15="","",P15+N(Q15)+N(R15)-N(S15)) -> 0
... P253: =IF(OR(F253="",O253=""),"",F253*O253) -> 0 | T253: =IF(P253="","",P253+N(Q253)+N(R253)-N(S253)) -> 0

Sheet Furniture Schedule
A1: Furniture Schedule
A2: Use filters in the header row. White cells are inputs; blue cells are formulas.
A3: Room | B3: Furniture Item | C3: Dimensions | D3: Quantity | E3: Vendor | F3: Product Link | G3: Fabric / Material | H3: Finish | I3: Cost | J3: Approval Status | K3: Order Status | L3: Delivery Date | M3: Install Date

Sheet Fixtures Schedule
A1: Fixtures Schedule
A2: Use filters in the header row. White cells are inputs; blue cells are formulas.
A3: Room | B3: Fixture Type | C3: Item Name | D3: Finish | E3: Size | F3: Vendor | G3: Model / SKU | H3: Quantity | I3: Unit Cost | J3: Total Cost | K3: Required Rough-in Date | L3: Order Deadline | M3: Delivery Date | N3: Installer Notes
J4: =IF(OR(H4="",I4=""),"",H4*I4) -> 0
J5: =IF(OR(H5="",I5=""),"",H5*I5) -> 0
J6: =IF(OR(H6="",I6=""),"",H6*I6) -> 0
J7: =IF(OR(H7="",I7=""),"",H7*I7) -> 0
J8: =IF(OR(H8="",I8=""),"",H8*I8) -> 0
J9: =IF(OR(H9="",I9=""),"",H9*I9) -> 0
J10: =IF(OR(H10="",I10=""),"",H10*I10) -> 0
J11: =IF(OR(H11="",I11=""),"",H11*I11) -> 0
J12: =IF(OR(H12="",I12=""),"",H12*I12) -> 0
J13: =IF(OR(H13="",I13=""),"",H13*I13) -> 0
J14: =IF(OR(H14="",I14=""),"",H14*I14) -> 0
J15: =IF(OR(H15="",I15=""),"",H15*I15) -> 0
... J253: =IF(OR(H253="",I253=""),"",H253*I253) -> 0

Sheet Finishes Schedule
A1: Finishes Schedule
A2: Use filters in the header row. White cells are inputs; blue cells are formulas.
A3: Room | B3: Surface / Application | C3: Finish Type | D3: Product Name | E3: Color / Finish | F3: Material | G3: Vendor | H3: Product Link | I3: SKU | J3: Quantity Needed | K3: Unit Cost | L3: Total Cost | M3: Sample Ordered | N3: Sample Approved | O3: Installer Notes
L4: =IF(OR(J4="",K4=""),"",J4*K4) -> 0
L5: =IF(OR(J5="",K5=""),"",J5*K5) -> 0
L6: =IF(OR(J6="",K6=""),"",J6*K6) -> 0
L7: =IF(OR(J7="",K7=""),"",J7*K7) -> 0
L8: =IF(OR(J8="",K8=""),"",J8*K8) -> 0
L9: =IF(OR(J9="",K9=""),"",J9*K9) -> 0
L10: =IF(OR(J10="",K10=""),"",J10*K10) -> 0
L11: =IF(OR(J11="",K11=""),"",J11*K11) -> 0
L12: =IF(OR(J12="",K12=""),"",J12*K12) -> 0
L13: =IF(OR(J13="",K13=""),"",J13*K13) -> 0
L14: =IF(OR(J14="",K14=""),"",J14*K14) -> 0
L15: =IF(OR(J15="",K15=""),"",J15*K15) -> 0
... L253: =IF(OR(J253="",K253=""),"",J253*K253) -> 0

Sheet Product Sourcing
A1: Product Sourcing
A2: Use filters in the header row. White cells are inputs; blue cells are formulas.
A3: Room | B3: Item Needed | C3: Option 1 Link | D3: Option 1 Price | E3: Option 2 Link | F3: Option 2 Price | G3: Option 3 Link | H3: Option 3 Price | I3: Preferred Option | J3: Pros | K3: Cons | L3: Client Feedback | M3: Final Selection

Sheet Vendor Database
A1: Vendor Database
A2: Use filters in the header row. White cells are inputs; blue cells are formulas.
A3: Vendor Name | B3: Vendor Type | C3: Contact Person | D3: Email | E3: Phone | F3: Website | G3: Account Number | H3: Trade Discount % | I3: Lead Time | J3: Shipping Terms | K3: Return Policy | L3: Notes

Sheet Budget Tracker
A1: Budget Tracker
A2: Use filters in the header row. White cells are inputs; blue cells are formulas.
A3: Budget Category | B3: Budgeted Amount | C3: Estimated Amount | D3: Actual Amount | E3: Difference | F3: Paid Amount | G3: Balance Due | H3: Payment Status | I3: Notes
A4: Furniture | E4: =IF(B4="","",B4-D4) -> 0 | G4: =IF(D4="","",D4-N(F4)) -> 0
A5: Lighting | E5: =IF(B5="","",B5-D5) -> 0 | G5: =IF(D5="","",D5-N(F5)) -> 0
A6: Rugs | E6: =IF(B6="","",B6-D6) -> 0 | G6: =IF(D6="","",D6-N(F6)) -> 0
A7: Decor | E7: =IF(B7="","",B7-D7) -> 0 | G7: =IF(D7="","",D7-N(F7)) -> 0
A8: Artwork | E8: =IF(B8="","",B8-D8) -> 0 | G8: =IF(D8="","",D8-N(F8)) -> 0
A9: Window treatments | E9: =IF(B9="","",B9-D9) -> 0 | G9: =IF(D9="","",D9-N(F9)) -> 0
A10: Flooring | E10: =IF(B10="","",B10-D10) -> 0 | G10: =IF(D10="","",D10-N(F10)) -> 0
A11: Paint/wallcovering | E11: =IF(B11="","",B11-D11) -> 0 | G11: =IF(D11="","",D11-N(F11)) -> 0
A12: Contractor labor | E12: =IF(B12="","",B12-D12) -> 0 | G12: =IF(D12="","",D12-N(F12)) -> 0
A13: Installation | E13: =IF(B13="","",B13-D13) -> 0 | G13: =IF(D13="","",D13-N(F13)) -> 0
A14: Shipping | E14: =IF(B14="","",B14-D14) -> 0 | G14: =IF(D14="","",D14-N(F14)) -> 0
A15: Taxes | E15: =IF(B15="","",B15-D15) -> 0 | G15: =IF(D15="","",D15-N(F15)) -> 0
... A17: Contingency | E17: =IF(B17="","",B17-D17) -> 0 | G17: =IF(D17="","",D17-N(F17)) -> 0
E18: =IF(B18="","",B18-D18) -> 0 | G18: =IF(D18="","",D18-N(F18)) -> 0
E19: =IF(B19="","",B19-D19) -> 0 | G19: =IF(D19="","",D19-N(F19)) -> 0
E20: =IF(B20="","",B20-D20) -> 0 | G20: =IF(D20="","",D20-N(F20)) -> 0
E21: =IF(B21="","",B21-D21) -> 0 | G21: =IF(D21="","",D21-N(F21)) -> 0
E22: =IF(B22="","",B22-D22) -> 0 | G22: =IF(D22="","",D22-N(F22)) -> 0
E23: =IF(B23="","",B23-D23) -> 0 | G23: =IF(D23="","",D23-N(F23)) -> 0
E24: =IF(B24="","",B24-D24) -> 0 | G24: =IF(D24="","",D24-N(F24)) -> 0
E25: =IF(B25="","",B25-D25) -> 0 | G25: =IF(D25="","",D25-N(F25)) -> 0
E26: =IF(B26="","",B26-D26) -> 0 | G26: =IF(D26="","",D26-N(F26)) -> 0
E27: =IF(B27="","",B27-D27) -> 0 | G27: =IF(D27="","",D27-N(F27)) -> 0
E28: =IF(B28="","",B28-D28) -> 0 | G28: =IF(D28="","",D28-N(F28)) -> 0
E29: =IF(B29="","",B29-D29) -> 0 | G29: =IF(D29="","",D29-N(F29)) -> 0
... E253: =IF(B253="","",B253-D253) -> 0 | G253: =IF(D253="","",D253-N(F253)) -> 0
A255: TOTAL | B255: =SUM(B4:B253) -> 0 | C255: =SUM(C4:C253) -> 0 | D255: =SUM(D4:D253) -> 0 | E255: =SUM(E4:E253) -> 0 | F255: =SUM(F4:F253) -> 0 | G255: =SUM(G4:G253) -> 0

Sheet Order Tracker
A1: Order Tracker
A2: Use filters in the header row. White cells are inputs; blue cells are formulas.
A3: PO Number | B3: Vendor | C3: Room | D3: Item | E3: Quantity | F3: Order Date | G3: Expected Ship Date | H3: Expected Delivery Date | I3: Actual Delivery Date | J3: Order Status | K3: Tracking Number | L3: Carrier | M3: Invoice Number | N3: Amount | O3: Paid Status | P3: Notes

Sheet Delivery & Installation
A1: Delivery & Installation
A2: Use filters in the header row. White cells are inputs; blue cells are formulas.
A3: Item | B3: Room | C3: Vendor | D3: Delivery Address | E3: Expected Delivery Date | F3: Actual Delivery Date | G3: Delivery Status | H3: Received By | I3: Damage Check | J3: Damage Notes | K3: Storage Location | L3: Install Date | M3: Installer | N3: Installation Status | O3: Punch List Notes

Sheet Client Approvals
A1: Client Approvals
A2: Use filters in the header row. White cells are inputs; blue cells are formulas.
A3: Item / Design Decision | B3: Room | C3: Approval Type | D3: Sent to Client Date | E3: Client Response Date | F3: Status | G3: Approved Option | H3: Client Comments | I3: Revision Needed | J3: Final Approval Date

Sheet Project Timeline
A1: Project Timeline
A2: Enter task dates, then set the Gantt start date in K2. Weekly bars shade automatically. | K2: Gantt start: | L2: =TODAY()-WEEKDAY(TODAY(),2)+1 -> 0
A3: Phase | B3: Task | C3: Assigned To | D3: Start Date | E3: Due Date | F3: Completion Date | G3: Status | H3: Priority | I3: Dependencies | J3: Notes | K3: =$L$2+0*7 -> 0 | L3: =$L$2+1*7 -> 0 | M3: =$L$2+2*7 -> 0 | N3: =$L$2+3*7 -> 0 | O3: =$L$2+4*7 -> 0 | P3: =$L$2+5*7 -> 0 | Q3: =$L$2+6*7 -> 0 | R3: =$L$2+7*7 -> 0 | S3: =$L$2+8*7 -> 0 | T3: =$L$2+9*7 -> 0 | U3: =$L$2+10*7 -> 0 | V3: =$L$2+11*7 -> 0 | W3: =$L$2+12*7 -> 0 | X3: =$L$2+13*7 -> 0 | Y3: =$L$2+14*7 -> 0 | Z3: =$L$2+15*7 -> 0 | AA3: =$L$2+16*7 -> 0 | AB3: =$L$2+17*7 -> 0 | AC3: =$L$2+18*7 -> 0 | AD3: =$L$2+19*7 -> 0 | AE3: =$L$2+20*7 -> 0 | AF3: =$L$2+21*7 -> 0 | AG3: =$L$2+22*7 -> 0 | AH3: =$L$2+23*7 -> 0 | AI3: =$L$2+24*7 -> 0 | AJ3: =$L$2+25*7 -> 0

Sheet Task List
A1: Task List
A2: Use filters in the header row. White cells are inputs; blue cells are formulas.
A3: Task | B3: Room | C3: Category | D3: Assigned To | E3: Priority | F3: Due Date | G3: Status | H3: Notes

Sheet Measurement Log
A1: Measurement Log
A2: Use filters in the header row. White cells are inputs; blue cells are formulas.
A3: Room | B3: Measurement Type | C3: Width | D3: Height | E3: Depth | F3: Length | G3: Ceiling Height | H3: Window Size | I3: Door Size | J3: Wall Length | K3: Notes

Sheet Contractor Tracker
A1: Contractor Tracker
A2: Use filters in the header row. White cells are inputs; blue cells are formulas.
A3: Contractor / Vendor Name | B3: Trade | C3: Contact | D3: Scope | E3: Quote Amount | F3: Start Date | G3: End Date | H3: Payment Status | I3: Insurance Received | J3: Contract Signed | K3: Notes

Sheet Invoice & Payment
A1: Invoice & Payment
A2: Use filters in the header row. White cells are inputs; blue cells are formulas.
A3: Invoice Number | B3: Invoice Date | C3: Client | D3: Description | E3: Amount | F3: Due Date | G3: Paid Date | H3: Payment Status | I3: Payment Method | J3: Notes

Sheet Project Notes
A1: Project Notes
A2: Use filters in the header row. White cells are inputs; blue cells are formulas.
A3: Date | B3: Meeting Type | C3: Attendees | D3: Discussion Points | E3: Decisions Made | F3: Action Items | G3: Follow-up Date | H3: Notes

Sheet Client FF&E Report
A1: CLIENT FF&E SPECIFICATION REPORT
A2: Client-facing live report. Use print settings or filter the Master FF&E tab before sharing.
A4: Item ID | B4: Room | C4: Category | D4: Item | E4: Description | F4: Qty | G4: Dimensions | H4: Material | I4: Finish | J4: Color | K4: Vendor | L4: Brand | M4: Product Link | N4: SKU | O4: Unit Cost | P4: Total | Q4: Tax | R4: Shipping | S4: Discount | T4: Final Cost | U4: Lead Time | V4: Order | W4: Approval | X4: Delivery | Y4: Install | Z4: Notes | AA4: Image
A5: {=IFERROR(_xlfn._xlws.FILTER('Master FF&E'!A4:AA253,'Master FF&E'!A4:A253<>""),"")} -> 0 | B5: 0 | C5: 0 | D5: 0 | E5: 0 | F5: 0 | G5: 0 | H5: 0 | I5: 0 | J5: 0 | K5: 0 | L5: 0 | M5: 0 | N5: 0 | O5: 0 | P5: 0 | Q5: 0 | R5: 0 | S5: 0 | T5: 0 | U5: 0 | V5: 0 | W5: 0 | X5: 0 | Y5: 0 | Z5: 0 | AA5: 0

Sheet Room Budget Report
A1: ROOM-BY-ROOM BUDGET REPORT
A2: Live summary of room allocations and spend.
A4: Room | B4: Type | C4: Floor | D4: Sq Ft | E4: Status | F4: Budget | G4: Estimated | H4: Actual | I4: Remaining | J4: Priority | K4: Notes
A5: {=IFERROR(_xlfn._xlws.FILTER('Room List'!A4:K253,'Room List'!A4:A253<>""),"")} -> 0 | B5: 0 | C5: 0 | D5: 0 | E5: 0 | F5: 0 | G5: 0 | H5: 0 | I5: 0 | J5: 0 | K5: 0

Sheet Vendor Order Report
A1: VENDOR ORDER REPORT
A2: Live purchasing report. Filter the Order Tracker by vendor or status for targeted reports.
A4: PO | B4: Vendor | C4: Room | D4: Item | E4: Qty | F4: Order Date | G4: Expected Ship | H4: Expected Delivery | I4: Actual Delivery | J4: Status | K4: Tracking | L4: Carrier | M4: Invoice | N4: Amount | O4: Paid | P4: Notes
A5: {=IFERROR(_xlfn._xlws.FILTER('Order Tracker'!A4:P253,'Order Tracker'!A4:A253<>""),"")} -> 0 | B5: 0 | C5: 0 | D5: 0 | E5: 0 | F5: 0 | G5: 0 | H5: 0 | I5: 0 | J5: 0 | K5: 0 | L5: 0 | M5: 0 | N5: 0 | O5: 0 | P5: 0

Sheet Installation Checklist
A1: DELIVERY & INSTALLATION CHECKLIST
A2: Print-ready field checklist for receiving and installation days.
A4: Item | B4: Room | C4: Vendor | D4: Address | E4: Expected | F4: Actual | G4: Delivery Status | H4: Received By | I4: Damage Check | J4: Damage Notes | K4: Storage | L4: Install Date | M4: Installer | N4: Install Status | O4: Punch List
A5: {=IFERROR(_xlfn._xlws.FILTER('Delivery & Installation'!A4:O253,'Delivery & Installation'!A4:A253<>""),"")} -> 0 | B5: 0 | C5: 0 | D5: 0 | E5: 0 | F5: 0 | G5: 0 | H5: 0 | I5: 0 | J5: 0 | K5: 0 | L5: 0 | M5: 0 | N5: 0 | O5: 0

Sheet Final Punch List
A1: FINAL PUNCH LIST
A2: Shows records with punch-list notes. Keep this report internal until ready to share.
A4: Item | B4: Room | C4: Vendor | D4: Address | E4: Expected | F4: Actual | G4: Delivery Status | H4: Received By | I4: Damage Check | J4: Damage Notes | K4: Storage | L4: Install Date | M4: Installer | N4: Install Status | O4: Punch List
A5: {=IFERROR(_xlfn._xlws.FILTER('Delivery & Installation'!A4:O253,'Delivery & Installation'!O4:O253<>""),"")} -> 0 | B5: 0 | C5: 0 | D5: 0 | E5: 0 | F5: 0 | G5: 0 | H5: 0 | I5: 0 | J5: 0 | K5: 0 | L5: 0 | M5: 0 | N5: 0 | O5: 0

Sheet Lists
A1: RoomTypes | B1: ProjectTypes | C1: ProjectStatuses | D1: BillingMethods | E1: YesNo | F1: Priorities | G1: DesignStatuses | H1: Categories | I1: ApprovalStatuses | J1: OrderStatuses | K1: DeliveryStatuses | L1: InstallStatuses | M1: FixtureTypes | N1: FinishTypes | O1: Surfaces | P1: VendorTypes | Q1: BudgetCategories | R1: PaymentStatuses | S1: DamageChecks | T1: ApprovalTypes | U1: ApprovalTrackerStatuses | V1: Phases | W1: TaskStatuses | X1: MeasurementTypes | Y1: Trades | Z1: InvoiceStatuses | AA1: MeetingTypes
A2: Living room | B2: Residential | C2: Not started | D2: Flat fee | E2: Yes | F2: Low | G2: Not started | H2: Sofa | I2: Not sent | J2: Not ordered | K2: Not scheduled | L2: Not ready | M2: Lighting | N2: Paint | O2: Wall | P2: Furniture | Q2: Furniture | R2: Not paid | S2: Not checked | T2: Furniture | U2: Not sent | V2: Consultation | W2: Not started | X2: Room | Y2: General contractor | Z2: Draft | AA2: Client consultation
A3: Bedroom | B3: Commercial | C3: Planning | D3: Hourly | E3: No | F3: Medium | G3: Concept | H3: Chair | I3: Sent | J3: Sourcing | K3: Scheduled | L3: Ready to install | M3: Faucet | N3: Wallpaper | O3: Ceiling | P3: Lighting | Q3: Lighting | R3: Deposit paid | S3: Good condition | T3: Finish | U3: Sent | V3: Measurements | W3: In progress | X3: Wall | Y3: Painter | Z3: Sent | AA3: Vendor meeting
A4: Kitchen | B4: Office | C4: In progress | D4: Percentage | F4: High | G4: Sourcing | H4: Table | I4: Client review | J4: Option selected | K4: In transit | L4: Scheduled | M4: Sink | N4: Flooring | O4: Floor | P4: Fabric | Q4: Rugs | R4: Partially paid | S4: Damaged | T4: Layout | U4: Approved | V4: Concept design | W4: Waiting on client | X4: Window | Y4: Electrician | Z4: Paid | AA4: Site visit
A5: Bathroom | B5: Retail | C5: On hold | D5: Hybrid | F5: Urgent | G5: Client review | H5: Bed | I5: Approved | J5: Client review | K5: Delivered | L5: Installed | M5: Shower fixture | N5: Tile | O5: Cabinet | P5: Flooring | Q5: Decor | R5: Paid | S5: Missing item | T5: Color palette | U5: Revisions requested | V5: Sourcing | W5: Waiting on vendor | X5: Door | Y5: Plumber | Z5: Partially paid | AA5: Installation meeting
A6: Dining room | B6: Hospitality | C6: Complete | G6: Approved | H6: Rug | I6: Revisions requested | J6: Approved | K6: Delayed | L6: Punch list | M6: Tub | N6: Countertop | O6: Countertop | P6: Tile | Q6: Artwork | R6: Overdue | S6: Wrong item | T6: Budget | U6: Rejected | V6: Client approval | W6: Complete | X6: Cabinet | Y6: Flooring installer | Z6: Overdue | AA6: Contractor meeting
A7: Entryway | B7: Staging | C7: Cancelled | G7: Ordered | H7: Lighting | I7: Rejected | J7: Ordered | K7: Cancelled | L7: Complete | M7: Toilet | N7: Backsplash | O7: Shower wall | P7: Paint | Q7: Window treatments | R7: Cancelled | T7: Purchase | U7: On hold | V7: Purchasing | W7: Delayed | X7: Furniture space | Y7: Tile installer | Z7: Cancelled | AA7: Final walkthrough
A8: Office | G8: Installed | H8: Artwork | I8: On hold | J8: Confirmed | K8: Returned | L8: On hold | M8: Cabinet hardware | N8: Cabinet finish | O8: Backsplash | P8: Wallpaper | Q8: Flooring | R8: Draft | T8: Vendor | V8: Construction | X8: Rug area | Y8: Wallpaper installer
A9: Nursery | G9: Complete | H9: Mirror | J9: In production | M9: Door hardware | N9: Fabric | O9: Upholstery | P9: Decor | Q9: Paint/wallcovering | R9: Sent | T9: Design concept | V9: Delivery | X9: Lighting location | Y9: Carpenter
A10: Outdoor | G10: On hold | H10: Window treatment | J10: Shipped | M10: Appliance | N10: Trim | O10: Drapery | P10: Hardware | Q10: Contractor labor | V10: Installation | Y10: Window treatment installer
A11: Commercial space | H11: Hardware | J11: Delivered | M11: Electrical | N11: Stone | O11: Other | P11: Contractor | Q11: Installation | V11: Styling | Y11: Furniture installer
A12: Other | H12: Plumbing fixture | J12: Delayed | M12: Other | N12: Wood | P12: Installer | Q12: Shipping | V12: Final reveal | Y12: Cleaner
H13: Appliance | J13: Cancelled | N13: Metal | P13: Workroom | Q13: Taxes | V13: Punch list | Y13: Other
H14: Decor | J14: Returned | N14: Other | P14: Custom furniture | Q14: Design fee
H15: Textile | J15: Backordered | P15: Other | Q15: Contingency
H16: Cabinetry
H17: Flooring
H18: Wallcovering
H19: Other
